<?xml version="1.0" encoding="UTF-8"?>
<flow id="69f57bd8-4e92-4cac-9466-75e3d2ccf09f">
  <descriptionCdata><![CDATA[69f57bd8-4e92-4cac-9466-75e3d2ccf09f.9db8686c-9966-4d9c-a5fb-c3f1b5888476.callout=To create a flow, delete the Success or Failure step and then find the operations that you want in the Dependencies tree and Projects tree to the left and drag them onto this canvas.  Wire them together to create a flow. Save the flow and then execute it in Operations Orchestration Central.
69f57bd8-4e92-4cac-9466-75e3d2ccf09f.description=<pre>\nUse this template when you are creating a new flow. You should remove the Success or Failure step.\n\nResponses\:\n    success - the flow completed successfully.\n    failure - the flow completed unsuccessfully.\n</pre>
69f57bd8-4e92-4cac-9466-75e3d2ccf09f.f3a8d796-a056-4309-8bfe-15bd705cb1a1.description=<pre>This is an operation that ask the user if the flow execution should go to success or not and based on the selection the flow goes to success or failure.\n\nInputs\:\n    goToSucces - required input that can be used to decide the final execution of the flow\: success or failure.\n    Field_1 - optional input that can be used for filtering flow variables.\n    Field_2 - optional input that can be used for filtering flow variables.\n    Field_3 - optional input that can be used for filtering flow variables.\n    Field_4 - optional input that can be used for filtering flow variables.\n\nResponses\:\n    success\n    failure\n</pre>
]]></descriptionCdata>
  <annotation>69f57bd8-4e92-4cac-9466-75e3d2ccf09f.description</annotation>
  <name>AIG F5 Provision Pool</name>
  <categories/>
  <inputs/>
  <possibleResponses>
    <opResponse id="2815cc0c-a48a-4d38-b377-13465ccca9c8">
      <annotation></annotation>
      <name>success</name>
      <isDefault>true</isDefault>
      <onFailure>false</onFailure>
      <type>RESOLVED</type>
      <matchRules/>
    </opResponse>
    <opResponse id="36e6262f-ea23-4897-8ed0-bc849b7238a9">
      <annotation></annotation>
      <name>failure</name>
      <isDefault>false</isDefault>
      <onFailure>true</onFailure>
      <type>ERROR</type>
      <matchRules/>
    </opResponse>
  </possibleResponses>
  <availableResultExpressions/>
  <resultExpression id="636e940d-c453-43ab-a441-757214df7026">
    <annotation></annotation>
    <name>FailureMessage</name>
    <fieldName>FailureMessage</fieldName>
    <sourceType>RAWRESULT</sourceType>
    <filters/>
  </resultExpression>
  <iconSpec id="8e58b957-4755-4ff8-940c-1716ea10c30f">
    <baseIcon>flow.png</baseIcon>
    <basePath>System</basePath>
    <readOnly>false</readOnly>
    <layers/>
  </iconSpec>
  <callouts>
    <callout id="9db8686c-9966-4d9c-a5fb-c3f1b5888476">
      <text>69f57bd8-4e92-4cac-9466-75e3d2ccf09f.9db8686c-9966-4d9c-a5fb-c3f1b5888476.callout</text>
      <bounds>
        <x>138.0</x>
        <y>117.0</y>
        <width>213.0</width>
        <height>124.0</height>
      </bounds>
      <layer>-1</layer>
    </callout>
  </callouts>
  <checkPointFlow>true</checkPointFlow>
  <compatibleRuntimeContext>false</compatibleRuntimeContext>
  <historyCheckPointFlow>true</historyCheckPointFlow>
  <steps>
    <step id="f3a8d796-a056-4309-8bfe-15bd705cb1a1">
      <annotation>69f57bd8-4e92-4cac-9466-75e3d2ccf09f.f3a8d796-a056-4309-8bfe-15bd705cb1a1.description</annotation>
      <name>Success or Failure</name>
      <bounds>
        <x>0.0</x>
        <y>0.0</y>
      </bounds>
      <layer>-1</layer>
      <hideInbound>false</hideInbound>
      <iconSpec id="d9da9fe1-0a01-4242-a85b-c39ccd80cc16">
        <baseIcon>display_report.png</baseIcon>
        <basePath>Utilities/</basePath>
        <readOnly>false</readOnly>
        <layers/>
      </iconSpec>
      <addResultToRunContext>false</addResultToRunContext>
      <isCriticalStep>false</isCriticalStep>
      <isNonBlocking>false</isNonBlocking>
      <isParallelStep>false</isParallelStep>
      <isSingleResponse>false</isSingleResponse>
      <recordInHistory>false</recordInHistory>
      <recordRawOutput>true</recordRawOutput>
      <recordPrimaryOutput>true</recordPrimaryOutput>
      <checkPointStep>true</checkPointStep>
      <historyCheckPointStep>true</historyCheckPointStep>
      <scriptResultStep>false</scriptResultStep>
      <userPrompt></userPrompt>
      <scriptlet id="c8c0a4ee-11eb-43c5-93b3-91af7f5c6a03">
        <annotation></annotation>
        <name>Step Success or Failure in Flow F5 Provision Pool (f3a8d796-a056-4309-8bfe-15bd705cb1a1)</name>
        <script>if (&quot;undefined&quot; == typeof goToSuccess) {
    goToSuccess = &quot;no&quot;;
}
if(goToSuccess.equalsIgnoreCase(&quot;yes&quot;)) {
	scriptletResult = &quot;success&quot;;
	scriptletResponse = &quot;success&quot;; 
	scriptletRawResult[&apos;returnCode&apos;] = &quot;0&quot;;
	scriptletContext.putGlobal(&apos;returnCode&apos;, &apos;0&apos;);
} else {
	scriptletResponse = &quot;failure&quot;;
	scriptletRawResult[&apos;returnCode&apos;] = &quot;1&quot;;
	scriptletContext.putGlobal(&apos;returnCode&apos;, &apos;1&apos;);
	scriptletResult = &quot;failure&quot;;
	scriptletContext.put(&quot;FailureMessage&quot;, &quot;failure&quot; );
}</script>
        <type>RHINO</type>
      </scriptlet>
      <bindings>
        <staticBinding id="65e34e6f-44e9-4266-be26-ad90c1163288">
          <annotation></annotation>
          <assignFromContext>true</assignFromContext>
          <assignToContext>true</assignToContext>
          <inputType>STRING</inputType>
          <isList>false</isList>
          <required>true</required>
          <isPersisted>true</isPersisted>
          <inputSymbol>goToSuccess</inputSymbol>
          <listDelimiter>,</listDelimiter>
          <value>yes</value>
          <record>false</record>
        </staticBinding>
        <staticBinding id="b852a058-f56f-405d-97fb-4a3a25819fce">
          <annotation></annotation>
          <assignFromContext>true</assignFromContext>
          <assignToContext>true</assignToContext>
          <inputType>STRING</inputType>
          <isList>false</isList>
          <required>false</required>
          <isPersisted>true</isPersisted>
          <inputSymbol>Field_1</inputSymbol>
          <listDelimiter>,</listDelimiter>
          <value></value>
          <record>false</record>
        </staticBinding>
        <staticBinding id="bf8d06f3-419f-49c3-acca-4c7bc5bc4f24">
          <annotation></annotation>
          <assignFromContext>true</assignFromContext>
          <assignToContext>true</assignToContext>
          <inputType>STRING</inputType>
          <isList>false</isList>
          <required>false</required>
          <isPersisted>true</isPersisted>
          <inputSymbol>Field_2</inputSymbol>
          <listDelimiter>,</listDelimiter>
          <value></value>
          <record>false</record>
        </staticBinding>
        <staticBinding id="55812767-066d-4700-8074-bfbed0403ee2">
          <annotation></annotation>
          <assignFromContext>true</assignFromContext>
          <assignToContext>true</assignToContext>
          <inputType>STRING</inputType>
          <isList>false</isList>
          <required>false</required>
          <isPersisted>true</isPersisted>
          <inputSymbol>Field_3</inputSymbol>
          <listDelimiter>,</listDelimiter>
          <value></value>
          <record>false</record>
        </staticBinding>
        <staticBinding id="c87a2282-7954-488b-9155-154ef3b8d3a5">
          <annotation></annotation>
          <assignFromContext>true</assignFromContext>
          <assignToContext>true</assignToContext>
          <inputType>STRING</inputType>
          <isList>false</isList>
          <required>false</required>
          <isPersisted>true</isPersisted>
          <inputSymbol>Field_4</inputSymbol>
          <listDelimiter>,</listDelimiter>
          <value></value>
          <record>false</record>
        </staticBinding>
      </bindings>
      <transitions>
        <transition id="e1a1d8da-47b6-4ee3-8a25-d591fe4a4061">
          <annotation></annotation>
          <name>success</name>
          <command>NEXT</command>
          <linkMode>false</linkMode>
          <responseSymbol>success</responseSymbol>
          <shouldHandoff>false</shouldHandoff>
          <transitionValue>0.0</transitionValue>
          <destination>
            <refId>d4d8c509-73a5-42e4-baf0-272d4c9f14ac</refId>
          </destination>
          <source>
            <refId>f3a8d796-a056-4309-8bfe-15bd705cb1a1</refId>
          </source>
          <positions>
            <point>
              <x>50.0</x>
              <y>34.0</y>
            </point>
            <point>
              <x>225.0</x>
              <y>34.0</y>
            </point>
          </positions>
          <labelPosition>
            <x>451.14702512245316</x>
            <y>-9.366765419852896</y>
          </labelPosition>
        </transition>
        <transition id="7ed7c548-e96b-48c6-9311-15ec961c1f9e">
          <annotation></annotation>
          <name>failure</name>
          <command>NEXT</command>
          <linkMode>false</linkMode>
          <responseSymbol>failure</responseSymbol>
          <shouldHandoff>false</shouldHandoff>
          <transitionValue>0.0</transitionValue>
          <destination>
            <refId>0def3c57-e0bb-4345-8c8d-fd163182150c</refId>
          </destination>
          <source>
            <refId>f3a8d796-a056-4309-8bfe-15bd705cb1a1</refId>
          </source>
          <positions>
            <point>
              <x>50.0</x>
              <y>34.0</y>
            </point>
            <point>
              <x>50.0</x>
              <y>194.0</y>
            </point>
          </positions>
          <labelPosition>
            <x>549.860738142368</x>
            <y>18.382570482504637</y>
          </labelPosition>
        </transition>
      </transitions>
      <properties/>
      <opRef>
        <refId>e46b91b4-6637-4b3d-883a-e86436d9eb3a</refId>
      </opRef>
      <assignments>
        <flowVariableAssignment id="99386649-c4d6-4fb9-98e5-5393368c9c22">
          <annotation></annotation>
          <name>assignment</name>
          <action>OVERWRITE</action>
          <assignmentTargetType>FLOW_VARIABLE</assignmentTargetType>
          <contextKey>Field_1</contextKey>
          <expression id="97e8532d-104b-48fb-9170-f1ba685d292f">
            <annotation></annotation>
            <name>Result Field: Field_1</name>
            <fieldName>Field_1</fieldName>
            <sourceType>RAWRESULT</sourceType>
            <filters/>
          </expression>
        </flowVariableAssignment>
      </assignments>
      <throttleSize>0</throttleSize>
    </step>
    <returnStep id="d4d8c509-73a5-42e4-baf0-272d4c9f14ac">
      <annotation></annotation>
      <name>Resolved : success</name>
      <bounds>
        <x>175.0</x>
        <y>0.0</y>
      </bounds>
      <layer>-1</layer>
      <hideInbound>false</hideInbound>
      <iconSpec id="bda06ccd-ac09-4caf-a456-44253abc3c4f">
        <baseIcon>return_success.png</baseIcon>
        <basePath>System</basePath>
        <readOnly>true</readOnly>
        <layers/>
      </iconSpec>
      <addResultToRunContext>false</addResultToRunContext>
      <isCriticalStep>false</isCriticalStep>
      <isNonBlocking>false</isNonBlocking>
      <isParallelStep>false</isParallelStep>
      <isSingleResponse>false</isSingleResponse>
      <recordInHistory>false</recordInHistory>
      <recordRawOutput>true</recordRawOutput>
      <recordPrimaryOutput>true</recordPrimaryOutput>
      <checkPointStep>true</checkPointStep>
      <historyCheckPointStep>true</historyCheckPointStep>
      <scriptResultStep>false</scriptResultStep>
      <userPrompt></userPrompt>
      <bindings/>
      <transitions>
        <transition id="721563e4-1fde-44fa-96b1-332f530b288c">
          <annotation></annotation>
          <name>return</name>
          <command>NEXT</command>
          <linkMode>false</linkMode>
          <responseSymbol>success</responseSymbol>
          <shouldHandoff>false</shouldHandoff>
          <transitionValue>0.0</transitionValue>
          <destination>
            <refId>d4d8c509-73a5-42e4-baf0-272d4c9f14ac</refId>
          </destination>
          <source>
            <refId>d4d8c509-73a5-42e4-baf0-272d4c9f14ac</refId>
          </source>
          <positions/>
        </transition>
      </transitions>
      <properties/>
      <returnStepType>RESOLVED</returnStepType>
      <assignments/>
    </returnStep>
    <returnStep id="0def3c57-e0bb-4345-8c8d-fd163182150c">
      <annotation></annotation>
      <name>Error : failure</name>
      <bounds>
        <x>0.0</x>
        <y>160.0</y>
      </bounds>
      <layer>-1</layer>
      <hideInbound>false</hideInbound>
      <addResultToRunContext>false</addResultToRunContext>
      <isCriticalStep>false</isCriticalStep>
      <isNonBlocking>false</isNonBlocking>
      <isParallelStep>false</isParallelStep>
      <isSingleResponse>false</isSingleResponse>
      <recordInHistory>false</recordInHistory>
      <recordRawOutput>true</recordRawOutput>
      <recordPrimaryOutput>true</recordPrimaryOutput>
      <checkPointStep>true</checkPointStep>
      <historyCheckPointStep>true</historyCheckPointStep>
      <scriptResultStep>false</scriptResultStep>
      <userPrompt></userPrompt>
      <bindings/>
      <transitions>
        <transition id="42511b9f-f081-498b-8a4f-861c29ce0154">
          <annotation></annotation>
          <name>return</name>
          <command>NEXT</command>
          <linkMode>false</linkMode>
          <responseSymbol>failure</responseSymbol>
          <shouldHandoff>false</shouldHandoff>
          <transitionValue>0.0</transitionValue>
          <destination>
            <refId>0def3c57-e0bb-4345-8c8d-fd163182150c</refId>
          </destination>
          <source>
            <refId>0def3c57-e0bb-4345-8c8d-fd163182150c</refId>
          </source>
          <positions/>
        </transition>
      </transitions>
      <properties/>
      <returnStepType>ERROR</returnStepType>
      <assignments/>
    </returnStep>
  </steps>
  <startSteps>f3a8d796-a056-4309-8bfe-15bd705cb1a1</startSteps>
</flow>