<?xml version="1.0" encoding="UTF-8"?>
<flow id="c29ff47a-4365-444e-bef7-66b10cb1f2ee">
  <descriptionCdata><![CDATA[c29ff47a-4365-444e-bef7-66b10cb1f2ee.0f8e30ea-773f-4da7-b1ce-3bbc7c92849b.description=<pre>\nThis operation does not do anything. It is useful to filter flow variables by feeding them as inputs and filtering them on the results tab.\n\nInputs\:\n    field1 \u2013 An optional input that can be used for filtering flow variables.\n    field2 \u2013 An optional input that can be used for filtering flow variables.\n    field3 \u2013 An optional input that can be used for filtering flow variables.\n    field4 \u2013 An optional input that can be used for filtering flow variables.\n\nResults\:\n    returnResult - This is the primary output. The value of the "field1", as it was specified at input or filtered. \n\nResponses\:\n    success - The operation completed as stated in the description.\n</pre>
c29ff47a-4365-444e-bef7-66b10cb1f2ee.5a64a9ca-0d14-457d-9b14-7ab8f5e0d28e.prompt=686f9cc2-9a85-4994-a290-358775e06208.21488540-7aca-4ad0-a285-04ae5bc20927.prompt
c29ff47a-4365-444e-bef7-66b10cb1f2ee.a155fa06-707c-441e-ae63-f3202da5ccf5.prompt=686f9cc2-9a85-4994-a290-358775e06208.c6466c36-d0cc-4e58-99c1-93936062db87.prompt
c29ff47a-4365-444e-bef7-66b10cb1f2ee.af134ceb-8553-42ce-bef9-4ea19d8167d0.description=<pre>\nCheck to see if the value stored in a specified flow variable, denoted by key, is null.\n\nInputs\:\nkeyName - The key to check, i.e. the name of the flow variable.\n\nReturns\: \nThe value in the specified key, i.e. flow variable.\n\nResponses\:\nisNull - If the key is a null pointer, i.e. the flow variable doesn't have an assigned value.\nnotNull - If some value is stored in the key, i.e the flow variable has a value assigned.\n</pre>
c29ff47a-4365-444e-bef7-66b10cb1f2ee.d956b6a2-26fc-49b6-8fc1-f8a695a41cac.description=<pre>\nThis operation iterates through a list of values. It is not recommended to modify the value of the "list" and "separator" inputs during the iteration process.\n\nInputs\:\n    list - The list to iterate through.\n    separator - A delimiter separating the list elements.\nDefault value\: \u2018,\u2019 (comma) \n\nResults\:\n    resultString - The current list element (if the response is "has more").\n\nResponses\:\n    has more - Another value was found in the list and it has been returned.\n    no more - The iterator has gone through the entire list. This response is returned once per list iteration.  A subsequent call to the \u201CList iterator\u201D operation restarts the list iteration process.\n    failure - The operation completed unsuccessfully.\n\nNote\:\n1. The position of the iterator in the list is tracked by each step's unique identifier. Therefore you can simultaneously iterate through the same list from multiple steps.\n</pre>
c29ff47a-4365-444e-bef7-66b10cb1f2ee.e5ce1c98-d890-4e1c-89c4-c2e99fe9c116.description=686f9cc2-9a85-4994-a290-358775e06208.5a2baca6-763a-4d64-bda6-c9de283767fc.description
c29ff47a-4365-444e-bef7-66b10cb1f2ee.fe6d117c-63ed-4b9f-a0ee-cd461ff07c28.description=<pre>Useful Op to keep a running results.\nTakes a string input (resultText) and appends this to a global context key of "runningResults". As a result, the context key whose name is in the keyName input will be appended with the string from the input resultText.\n\nInput Parameters\:\nkeyName - name of context key to append to\nresultText - string input to append\ndelimiter - (leave blank for none) the delimiter to put between what is already in keyName before appending resultText\n\nResponses\:\nsuccess - assigned the context variable\n\nReturns\:\nThe the value of the context variable it appended to.\n\nContext\:\nrunningResults\n\nScriptlet Example\:\ncurrentResults \= scriptletContext.get("runningResults");\n\nif (currentResults \=\= null) {\n   currentResults \= resultText;\n} else {\n   currentResults +\= resultText;\n}\n\n\nscriptletContext.putGlobal("runningResults", currentResults);</pre>
]]></descriptionCdata>
  <annotation></annotation>
  <name>F5_LB_Component_Deploy_Node</name>
  <categories/>
  <inputs>
    <userInputBinding id="904aba78-5eac-45b8-8af8-5ea53dd14b1f">
      <annotation></annotation>
      <assignFromContext>false</assignFromContext>
      <assignToContext>false</assignToContext>
      <inputType>STRING</inputType>
      <isList>false</isList>
      <required>true</required>
      <isPersisted>true</isPersisted>
      <inputSymbol>na_hostname</inputSymbol>
      <listDelimiter>,</listDelimiter>
      <record>false</record>
      <prompt></prompt>
      <isMultiSelect>false</isMultiSelect>
      <sourceDelimiter>|</sourceDelimiter>
    </userInputBinding>
    <staticBinding id="b37d2060-62fb-4784-88b8-f2a98b499662">
      <annotation></annotation>
      <assignFromContext>true</assignFromContext>
      <assignToContext>true</assignToContext>
      <inputType>STRING</inputType>
      <isList>false</isList>
      <required>false</required>
      <isPersisted>true</isPersisted>
      <inputSymbol>CSA_PROCESS_ID</inputSymbol>
      <listDelimiter>,</listDelimiter>
      <value>${CSA_PROCESS_ID}</value>
      <record>false</record>
    </staticBinding>
    <staticBinding id="faa07231-4acf-4629-a9bb-9d3f42476425">
      <annotation></annotation>
      <assignFromContext>false</assignFromContext>
      <assignToContext>false</assignToContext>
      <inputType>STRING</inputType>
      <isList>false</isList>
      <required>false</required>
      <isPersisted>true</isPersisted>
      <inputSymbol>artifact</inputSymbol>
      <listDelimiter>,</listDelimiter>
      <value>${artifact}</value>
      <record>false</record>
    </staticBinding>
    <staticBinding id="9274085c-9963-4835-932a-9a49d611920b">
      <annotation></annotation>
      <assignFromContext>true</assignFromContext>
      <assignToContext>true</assignToContext>
      <inputType>STRING</inputType>
      <isList>false</isList>
      <required>false</required>
      <isPersisted>true</isPersisted>
      <inputSymbol>RSC_PROVIDER_ID</inputSymbol>
      <listDelimiter>,</listDelimiter>
      <value>${RSC_PROVIDER_ID}</value>
      <record>false</record>
    </staticBinding>
    <staticBinding id="0c574c52-4939-4a7f-9605-46647fefe52b">
      <annotation></annotation>
      <assignFromContext>false</assignFromContext>
      <assignToContext>false</assignToContext>
      <inputType>STRING</inputType>
      <isList>false</isList>
      <required>false</required>
      <isPersisted>true</isPersisted>
      <inputSymbol>userIdentifier</inputSymbol>
      <listDelimiter>,</listDelimiter>
      <value>${userIdentifier}</value>
      <record>false</record>
    </staticBinding>
    <userInputBinding id="70b173b1-4f04-49b0-a965-a0388dc4af82">
      <annotation></annotation>
      <assignFromContext>false</assignFromContext>
      <assignToContext>false</assignToContext>
      <inputType>STRING</inputType>
      <isList>false</isList>
      <required>true</required>
      <isPersisted>true</isPersisted>
      <inputSymbol>na_port</inputSymbol>
      <listDelimiter>,</listDelimiter>
      <record>false</record>
      <prompt></prompt>
      <isMultiSelect>false</isMultiSelect>
      <sourceDelimiter>|</sourceDelimiter>
    </userInputBinding>
    <userInputBinding id="cf126081-b725-4ce5-8e3f-6dc3a8435b7a">
      <annotation></annotation>
      <assignFromContext>false</assignFromContext>
      <assignToContext>false</assignToContext>
      <inputType>STRING</inputType>
      <isList>false</isList>
      <required>true</required>
      <isPersisted>true</isPersisted>
      <inputSymbol>na_protocol</inputSymbol>
      <listDelimiter>,</listDelimiter>
      <record>false</record>
      <prompt></prompt>
      <isMultiSelect>false</isMultiSelect>
      <sourceDelimiter>|</sourceDelimiter>
    </userInputBinding>
    <userInputBinding id="be5a2659-c144-41ec-89b0-8e6a21605b0d">
      <annotation></annotation>
      <assignFromContext>false</assignFromContext>
      <assignToContext>false</assignToContext>
      <inputType>STRING</inputType>
      <isList>false</isList>
      <required>true</required>
      <isPersisted>true</isPersisted>
      <inputSymbol>na_user</inputSymbol>
      <listDelimiter>,</listDelimiter>
      <record>false</record>
      <prompt></prompt>
      <isMultiSelect>false</isMultiSelect>
      <sourceDelimiter>|</sourceDelimiter>
    </userInputBinding>
    <userInputBinding id="98befda6-b277-411c-a44b-7b9ce308bc21">
      <annotation></annotation>
      <assignFromContext>false</assignFromContext>
      <assignToContext>false</assignToContext>
      <inputType>STRING</inputType>
      <isList>false</isList>
      <required>true</required>
      <isPersisted>true</isPersisted>
      <inputSymbol>na_password</inputSymbol>
      <listDelimiter>,</listDelimiter>
      <record>false</record>
      <prompt></prompt>
      <isMultiSelect>false</isMultiSelect>
      <sourceDelimiter>|</sourceDelimiter>
    </userInputBinding>
    <userInputBinding id="d7e81a3e-1acc-4846-8f78-b88204849789">
      <annotation></annotation>
      <assignFromContext>false</assignFromContext>
      <assignToContext>false</assignToContext>
      <inputType>STRING</inputType>
      <isList>false</isList>
      <required>true</required>
      <isPersisted>true</isPersisted>
      <inputSymbol>fw_device_ip</inputSymbol>
      <listDelimiter>,</listDelimiter>
      <record>false</record>
      <prompt></prompt>
      <isMultiSelect>false</isMultiSelect>
      <sourceDelimiter>|</sourceDelimiter>
    </userInputBinding>
    <userInputBinding id="37f84a52-3f84-40a0-adf1-721b766e3b2f">
      <annotation></annotation>
      <assignFromContext>false</assignFromContext>
      <assignToContext>false</assignToContext>
      <inputType>STRING</inputType>
      <isList>false</isList>
      <required>true</required>
      <isPersisted>true</isPersisted>
      <inputSymbol>lb_virtual_server</inputSymbol>
      <listDelimiter>,</listDelimiter>
      <record>false</record>
      <prompt></prompt>
      <isMultiSelect>false</isMultiSelect>
      <sourceDelimiter>|</sourceDelimiter>
    </userInputBinding>
    <userInputBinding id="031e1339-6ed3-4a31-a5f0-bc99f59ceb4c">
      <annotation></annotation>
      <assignFromContext>false</assignFromContext>
      <assignToContext>false</assignToContext>
      <inputType>STRING</inputType>
      <isList>false</isList>
      <required>true</required>
      <isPersisted>true</isPersisted>
      <inputSymbol>lb_port</inputSymbol>
      <listDelimiter>,</listDelimiter>
      <record>false</record>
      <prompt></prompt>
      <isMultiSelect>false</isMultiSelect>
      <sourceDelimiter>|</sourceDelimiter>
    </userInputBinding>
    <userInputBinding id="0e9de3ea-c4e1-4d5a-b8b1-2ed4d3823332">
      <annotation></annotation>
      <assignFromContext>false</assignFromContext>
      <assignToContext>false</assignToContext>
      <inputType>STRING</inputType>
      <isList>false</isList>
      <required>true</required>
      <isPersisted>true</isPersisted>
      <inputSymbol>node_add</inputSymbol>
      <listDelimiter>,</listDelimiter>
      <record>false</record>
      <prompt></prompt>
      <isMultiSelect>false</isMultiSelect>
      <sourceDelimiter>|</sourceDelimiter>
    </userInputBinding>
    <userInputBinding id="71393478-a907-4707-8cf2-87b9134d508b">
      <annotation></annotation>
      <assignFromContext>false</assignFromContext>
      <assignToContext>false</assignToContext>
      <inputType>STRING</inputType>
      <isList>false</isList>
      <required>false</required>
      <isPersisted>true</isPersisted>
      <inputSymbol>node_list</inputSymbol>
      <listDelimiter>,</listDelimiter>
      <record>false</record>
      <prompt></prompt>
      <isMultiSelect>false</isMultiSelect>
      <sourceDelimiter>|</sourceDelimiter>
    </userInputBinding>
  </inputs>
  <possibleResponses>
    <opResponse id="73c011c5-80fc-4724-8092-c2d590c9a852">
      <annotation></annotation>
      <name>failure</name>
      <isDefault>false</isDefault>
      <onFailure>true</onFailure>
      <type>ERROR</type>
      <matchRules/>
    </opResponse>
    <opResponse id="526bfbe4-f26f-4f3e-a896-582de30c4265">
      <annotation></annotation>
      <name>success</name>
      <isDefault>true</isDefault>
      <onFailure>false</onFailure>
      <type>RESOLVED</type>
      <matchRules/>
    </opResponse>
  </possibleResponses>
  <availableResultExpressions>
    <expression id="f07278a3-3932-4897-9728-0cde21a7fc07">
      <annotation></annotation>
      <name>error_message</name>
      <fieldName>error_message</fieldName>
      <sourceType>RAWRESULT</sourceType>
      <filters/>
    </expression>
    <expression id="8e5e4a14-d10a-49cb-adb1-38195ea7a0a7">
      <annotation></annotation>
      <name>step_name</name>
      <fieldName>step_name</fieldName>
      <sourceType>RAWRESULT</sourceType>
      <filters/>
    </expression>
    <expression id="05f8d02b-0920-4979-9c91-e3cb8aee187e">
      <annotation></annotation>
      <name>sub_flow_name</name>
      <fieldName>sub_flow_name</fieldName>
      <sourceType>RAWRESULT</sourceType>
      <filters/>
    </expression>
  </availableResultExpressions>
  <resultExpression id="0fb9625b-46fb-470a-b59a-f958bbc0630a">
    <annotation></annotation>
    <name>FailureMessage</name>
    <fieldName>FailureMessage</fieldName>
    <sourceType>RAWRESULT</sourceType>
    <filters/>
  </resultExpression>
  <iconSpec id="1bd9fe04-d011-44fa-8102-ca26d8a6d778">
    <baseIcon>branch.png</baseIcon>
    <basePath>/Others/</basePath>
    <readOnly>false</readOnly>
    <layers/>
  </iconSpec>
  <callouts/>
  <checkPointFlow>true</checkPointFlow>
  <compatibleRuntimeContext>false</compatibleRuntimeContext>
  <historyCheckPointFlow>true</historyCheckPointFlow>
  <steps>
    <step id="af134ceb-8553-42ce-bef9-4ea19d8167d0">
      <annotation>c29ff47a-4365-444e-bef7-66b10cb1f2ee.af134ceb-8553-42ce-bef9-4ea19d8167d0.description</annotation>
      <name>node pool member list null?</name>
      <bounds>
        <x>123.0</x>
        <y>99.0</y>
      </bounds>
      <layer>-1</layer>
      <hideInbound>false</hideInbound>
      <addResultToRunContext>false</addResultToRunContext>
      <isCriticalStep>false</isCriticalStep>
      <isNonBlocking>false</isNonBlocking>
      <isParallelStep>false</isParallelStep>
      <isSingleResponse>false</isSingleResponse>
      <recordInHistory>false</recordInHistory>
      <recordRawOutput>true</recordRawOutput>
      <recordPrimaryOutput>true</recordPrimaryOutput>
      <checkPointStep>true</checkPointStep>
      <historyCheckPointStep>true</historyCheckPointStep>
      <scriptResultStep>false</scriptResultStep>
      <userPrompt></userPrompt>
      <bindings>
        <staticBinding id="bc8c4e74-8206-424d-be0a-edd9c1823b49">
          <annotation></annotation>
          <assignFromContext>false</assignFromContext>
          <assignToContext>false</assignToContext>
          <inputType>STRING</inputType>
          <isList>false</isList>
          <required>true</required>
          <isPersisted>true</isPersisted>
          <inputSymbol>keyName</inputSymbol>
          <listDelimiter>,</listDelimiter>
          <value>node_add</value>
          <record>false</record>
        </staticBinding>
      </bindings>
      <transitions>
        <transition id="c58c6c84-e64c-4c56-b46a-4a221e4f2738">
          <annotation></annotation>
          <name>notNull</name>
          <command>NEXT</command>
          <linkMode>false</linkMode>
          <responseSymbol>notNull</responseSymbol>
          <shouldHandoff>false</shouldHandoff>
          <transitionValue>0.0</transitionValue>
          <destination>
            <refId>d956b6a2-26fc-49b6-8fc1-f8a695a41cac</refId>
          </destination>
          <source>
            <refId>af134ceb-8553-42ce-bef9-4ea19d8167d0</refId>
          </source>
          <positions>
            <point>
              <x>173.0</x>
              <y>133.0</y>
            </point>
            <point>
              <x>170.0</x>
              <y>355.0</y>
            </point>
          </positions>
          <labelPosition>
            <x>333.0</x>
            <y>0.0</y>
          </labelPosition>
        </transition>
        <transition id="ff0db4dc-e3cc-47a9-872b-427a50f23c04">
          <annotation></annotation>
          <name>isNull</name>
          <command>NEXT</command>
          <linkMode>false</linkMode>
          <responseSymbol>isNull</responseSymbol>
          <shouldHandoff>false</shouldHandoff>
          <transitionValue>0.0</transitionValue>
          <destination>
            <refId>71f76481-e300-469b-a14a-7d4bbd8132a4</refId>
          </destination>
          <source>
            <refId>af134ceb-8553-42ce-bef9-4ea19d8167d0</refId>
          </source>
          <positions>
            <point>
              <x>218.0</x>
              <y>134.59288537549406</y>
            </point>
            <point>
              <x>506.0</x>
              <y>36.0</y>
            </point>
            <point>
              <x>930.0</x>
              <y>149.0</y>
            </point>
          </positions>
          <labelPosition>
            <x>333.0</x>
            <y>0.0</y>
          </labelPosition>
        </transition>
      </transitions>
      <properties/>
      <opRef>
        <refId>b9997f7f-d19c-4dc6-acc4-fa91a8644a38</refId>
      </opRef>
      <assignments/>
      <throttleSize>0</throttleSize>
    </step>
    <returnStep id="cee4738e-a1e6-4428-8cbe-fe346ffa630d">
      <annotation></annotation>
      <name>Error : failure</name>
      <bounds>
        <x>113.0</x>
        <y>309.0</y>
      </bounds>
      <layer>-1</layer>
      <hideInbound>false</hideInbound>
      <addResultToRunContext>false</addResultToRunContext>
      <isCriticalStep>false</isCriticalStep>
      <isNonBlocking>false</isNonBlocking>
      <isParallelStep>false</isParallelStep>
      <isSingleResponse>false</isSingleResponse>
      <recordInHistory>false</recordInHistory>
      <recordRawOutput>true</recordRawOutput>
      <recordPrimaryOutput>true</recordPrimaryOutput>
      <checkPointStep>true</checkPointStep>
      <historyCheckPointStep>true</historyCheckPointStep>
      <scriptResultStep>false</scriptResultStep>
      <userPrompt></userPrompt>
      <bindings/>
      <transitions>
        <transition id="b8054a53-e5a8-4cd2-955d-62f2028fb044">
          <annotation></annotation>
          <name>return</name>
          <command>NEXT</command>
          <linkMode>false</linkMode>
          <responseSymbol>failure</responseSymbol>
          <shouldHandoff>false</shouldHandoff>
          <transitionValue>0.0</transitionValue>
          <destination>
            <refId>cee4738e-a1e6-4428-8cbe-fe346ffa630d</refId>
          </destination>
          <source>
            <refId>cee4738e-a1e6-4428-8cbe-fe346ffa630d</refId>
          </source>
          <positions/>
        </transition>
      </transitions>
      <properties/>
      <returnStepType>ERROR</returnStepType>
      <assignments/>
    </returnStep>
    <returnStep id="b9205eb5-bfb2-45f8-80d0-9002c45ce869">
      <annotation></annotation>
      <name>Error : failure</name>
      <bounds>
        <x>857.0</x>
        <y>282.0</y>
      </bounds>
      <layer>-1</layer>
      <hideInbound>false</hideInbound>
      <addResultToRunContext>false</addResultToRunContext>
      <isCriticalStep>false</isCriticalStep>
      <isNonBlocking>false</isNonBlocking>
      <isParallelStep>false</isParallelStep>
      <isSingleResponse>false</isSingleResponse>
      <recordInHistory>false</recordInHistory>
      <recordRawOutput>true</recordRawOutput>
      <recordPrimaryOutput>true</recordPrimaryOutput>
      <checkPointStep>true</checkPointStep>
      <historyCheckPointStep>true</historyCheckPointStep>
      <scriptResultStep>false</scriptResultStep>
      <userPrompt></userPrompt>
      <bindings/>
      <transitions>
        <transition id="f873798e-d258-43a7-bf9a-40261a8c7df6">
          <annotation></annotation>
          <name>return</name>
          <command>NEXT</command>
          <linkMode>false</linkMode>
          <responseSymbol>failure</responseSymbol>
          <shouldHandoff>false</shouldHandoff>
          <transitionValue>0.0</transitionValue>
          <destination>
            <refId>b9205eb5-bfb2-45f8-80d0-9002c45ce869</refId>
          </destination>
          <source>
            <refId>b9205eb5-bfb2-45f8-80d0-9002c45ce869</refId>
          </source>
          <positions/>
        </transition>
      </transitions>
      <properties/>
      <returnStepType>ERROR</returnStepType>
      <assignments/>
    </returnStep>
    <returnStep id="71f76481-e300-469b-a14a-7d4bbd8132a4">
      <annotation></annotation>
      <name>Resolved : success</name>
      <bounds>
        <x>880.0</x>
        <y>99.0</y>
      </bounds>
      <layer>-1</layer>
      <hideInbound>false</hideInbound>
      <addResultToRunContext>false</addResultToRunContext>
      <isCriticalStep>false</isCriticalStep>
      <isNonBlocking>false</isNonBlocking>
      <isParallelStep>false</isParallelStep>
      <isSingleResponse>false</isSingleResponse>
      <recordInHistory>false</recordInHistory>
      <recordRawOutput>true</recordRawOutput>
      <recordPrimaryOutput>true</recordPrimaryOutput>
      <checkPointStep>true</checkPointStep>
      <historyCheckPointStep>true</historyCheckPointStep>
      <scriptResultStep>false</scriptResultStep>
      <userPrompt></userPrompt>
      <bindings/>
      <transitions>
        <transition id="7e09aa44-8850-4113-8900-6a5b03681db5">
          <annotation></annotation>
          <name>return</name>
          <command>NEXT</command>
          <linkMode>false</linkMode>
          <responseSymbol>success</responseSymbol>
          <shouldHandoff>false</shouldHandoff>
          <transitionValue>0.0</transitionValue>
          <destination>
            <refId>71f76481-e300-469b-a14a-7d4bbd8132a4</refId>
          </destination>
          <source>
            <refId>71f76481-e300-469b-a14a-7d4bbd8132a4</refId>
          </source>
          <positions/>
        </transition>
      </transitions>
      <properties/>
      <returnStepType>RESOLVED</returnStepType>
      <assignments/>
    </returnStep>
    <step id="d956b6a2-26fc-49b6-8fc1-f8a695a41cac">
      <annotation>c29ff47a-4365-444e-bef7-66b10cb1f2ee.d956b6a2-26fc-49b6-8fc1-f8a695a41cac.description</annotation>
      <name>List Iterator</name>
      <bounds>
        <x>279.0</x>
        <y>99.0</y>
      </bounds>
      <layer>-1</layer>
      <hideInbound>false</hideInbound>
      <addResultToRunContext>false</addResultToRunContext>
      <isCriticalStep>false</isCriticalStep>
      <isNonBlocking>false</isNonBlocking>
      <isParallelStep>false</isParallelStep>
      <isSingleResponse>false</isSingleResponse>
      <recordInHistory>false</recordInHistory>
      <recordRawOutput>true</recordRawOutput>
      <recordPrimaryOutput>true</recordPrimaryOutput>
      <checkPointStep>true</checkPointStep>
      <historyCheckPointStep>true</historyCheckPointStep>
      <scriptResultStep>false</scriptResultStep>
      <userPrompt></userPrompt>
      <bindings>
        <staticBinding id="d956d443-0f19-45bf-88bf-2dbf7fbb6796">
          <annotation></annotation>
          <assignFromContext>false</assignFromContext>
          <assignToContext>false</assignToContext>
          <inputType>STRING</inputType>
          <isList>false</isList>
          <required>true</required>
          <isPersisted>true</isPersisted>
          <inputSymbol>list</inputSymbol>
          <listDelimiter>,</listDelimiter>
          <value>${node_add}</value>
          <record>false</record>
        </staticBinding>
        <staticBinding id="258874c8-1a6e-4ee5-82f5-44173ca6e516">
          <annotation></annotation>
          <assignFromContext>false</assignFromContext>
          <assignToContext>false</assignToContext>
          <inputType>STRING</inputType>
          <isList>false</isList>
          <required>true</required>
          <isPersisted>true</isPersisted>
          <inputSymbol>separator</inputSymbol>
          <listDelimiter>,</listDelimiter>
          <value>,</value>
          <record>false</record>
        </staticBinding>
      </bindings>
      <transitions>
        <transition id="4e5762c6-5311-4494-9b7f-213f30f76915">
          <annotation></annotation>
          <name>has more</name>
          <command>NEXT</command>
          <linkMode>false</linkMode>
          <responseSymbol>has more</responseSymbol>
          <shouldHandoff>false</shouldHandoff>
          <transitionValue>0.0</transitionValue>
          <destination>
            <refId>27e39166-52ef-4977-bc8a-254457c85060</refId>
          </destination>
          <source>
            <refId>d956b6a2-26fc-49b6-8fc1-f8a695a41cac</refId>
          </source>
          <positions>
            <point>
              <x>170.0</x>
              <y>355.0</y>
            </point>
            <point>
              <x>379.0</x>
              <y>340.0</y>
            </point>
          </positions>
          <labelPosition>
            <x>333.0</x>
            <y>0.0</y>
          </labelPosition>
        </transition>
        <transition id="a9b93ccc-e5b4-4f57-8859-023c651bf330">
          <annotation></annotation>
          <name>failure</name>
          <command>NEXT</command>
          <linkMode>false</linkMode>
          <responseSymbol>failure</responseSymbol>
          <shouldHandoff>false</shouldHandoff>
          <transitionValue>0.0</transitionValue>
          <destination>
            <refId>cee4738e-a1e6-4428-8cbe-fe346ffa630d</refId>
          </destination>
          <source>
            <refId>d956b6a2-26fc-49b6-8fc1-f8a695a41cac</refId>
          </source>
          <positions>
            <point>
              <x>170.0</x>
              <y>355.0</y>
            </point>
            <point>
              <x>165.0</x>
              <y>500.0</y>
            </point>
          </positions>
          <labelPosition>
            <x>333.0</x>
            <y>0.0</y>
          </labelPosition>
        </transition>
        <transition id="3b7604a3-4ede-4a7f-9fa4-31dafbe660b9">
          <annotation></annotation>
          <name>no more</name>
          <command>NEXT</command>
          <linkMode>false</linkMode>
          <responseSymbol>no more</responseSymbol>
          <shouldHandoff>false</shouldHandoff>
          <transitionValue>0.0</transitionValue>
          <destination>
            <refId>0f8e30ea-773f-4da7-b1ce-3bbc7c92849b</refId>
          </destination>
          <source>
            <refId>d956b6a2-26fc-49b6-8fc1-f8a695a41cac</refId>
          </source>
          <positions>
            <point>
              <x>170.0</x>
              <y>355.0</y>
            </point>
            <point>
              <x>490.0</x>
              <y>132.0</y>
            </point>
          </positions>
          <labelPosition>
            <x>333.0</x>
            <y>0.0</y>
          </labelPosition>
        </transition>
      </transitions>
      <properties/>
      <opRef>
        <refId>cd75ca75-e64e-4b1e-9fe9-8dbc76f03865</refId>
      </opRef>
      <assignments>
        <flowVariableAssignment id="f80f422b-6d1b-409d-9a45-39c57ccec011">
          <annotation></annotation>
          <name>assignment</name>
          <action>OVERWRITE</action>
          <assignmentTargetType>FLOW_VARIABLE</assignmentTargetType>
          <contextKey>node_ip</contextKey>
          <expression id="a9b9c15a-3f65-426c-834c-1d7baad023e3">
            <annotation></annotation>
            <name>Result Field: resultString</name>
            <fieldName>resultString</fieldName>
            <sourceType>RAWRESULT</sourceType>
            <filters/>
          </expression>
        </flowVariableAssignment>
      </assignments>
      <throttleSize>0</throttleSize>
    </step>
    <step id="27e39166-52ef-4977-bc8a-254457c85060">
      <annotation></annotation>
      <name>F5_LB_Add_Node</name>
      <bounds>
        <x>270.0</x>
        <y>309.0</y>
      </bounds>
      <layer>-1</layer>
      <hideInbound>false</hideInbound>
      <addResultToRunContext>false</addResultToRunContext>
      <isCriticalStep>false</isCriticalStep>
      <isNonBlocking>false</isNonBlocking>
      <isParallelStep>false</isParallelStep>
      <isSingleResponse>false</isSingleResponse>
      <recordInHistory>false</recordInHistory>
      <recordRawOutput>true</recordRawOutput>
      <recordPrimaryOutput>true</recordPrimaryOutput>
      <checkPointStep>true</checkPointStep>
      <historyCheckPointStep>true</historyCheckPointStep>
      <scriptResultStep>false</scriptResultStep>
      <userPrompt></userPrompt>
      <bindings>
        <staticBinding id="01a560b3-9f46-47b4-ac17-5d0d30e78456">
          <annotation></annotation>
          <assignFromContext>false</assignFromContext>
          <assignToContext>false</assignToContext>
          <inputType>STRING</inputType>
          <isList>false</isList>
          <required>true</required>
          <isPersisted>true</isPersisted>
          <inputSymbol>node_ip</inputSymbol>
          <listDelimiter>,</listDelimiter>
          <value>${node_ip}</value>
          <record>false</record>
        </staticBinding>
        <staticBinding id="01a84c1c-21dd-469f-b88c-503d535e1632">
          <annotation></annotation>
          <assignFromContext>false</assignFromContext>
          <assignToContext>false</assignToContext>
          <inputType>STRING</inputType>
          <isList>false</isList>
          <required>false</required>
          <isPersisted>true</isPersisted>
          <inputSymbol>na_hostname</inputSymbol>
          <listDelimiter>,</listDelimiter>
          <value>${na_hostname}</value>
          <record>false</record>
        </staticBinding>
        <staticBinding id="500334e4-d028-4d09-905a-36c64bfba0ac">
          <annotation></annotation>
          <assignFromContext>false</assignFromContext>
          <assignToContext>false</assignToContext>
          <inputType>STRING</inputType>
          <isList>false</isList>
          <required>false</required>
          <isPersisted>true</isPersisted>
          <inputSymbol>na_port</inputSymbol>
          <listDelimiter>,</listDelimiter>
          <value>${na_port}</value>
          <record>false</record>
        </staticBinding>
        <staticBinding id="105a24f8-2ea7-47cb-afb6-fec6ff8de0ed">
          <annotation></annotation>
          <assignFromContext>false</assignFromContext>
          <assignToContext>false</assignToContext>
          <inputType>STRING</inputType>
          <isList>false</isList>
          <required>false</required>
          <isPersisted>true</isPersisted>
          <inputSymbol>na_protocol</inputSymbol>
          <listDelimiter>,</listDelimiter>
          <value>${na_protocol}</value>
          <record>false</record>
        </staticBinding>
        <staticBinding id="758b14cf-62c2-4d83-80b1-0d5a2a3f978d">
          <annotation></annotation>
          <assignFromContext>false</assignFromContext>
          <assignToContext>false</assignToContext>
          <inputType>STRING</inputType>
          <isList>false</isList>
          <required>false</required>
          <isPersisted>true</isPersisted>
          <inputSymbol>na_user</inputSymbol>
          <listDelimiter>,</listDelimiter>
          <value>${na_user}</value>
          <record>false</record>
        </staticBinding>
        <staticBinding id="b2f9eaf7-ce73-40a4-b781-ad1916dc0ac1">
          <annotation></annotation>
          <assignFromContext>false</assignFromContext>
          <assignToContext>false</assignToContext>
          <inputType>STRING</inputType>
          <isList>false</isList>
          <required>false</required>
          <isPersisted>true</isPersisted>
          <inputSymbol>na_password</inputSymbol>
          <listDelimiter>,</listDelimiter>
          <value>${na_password}</value>
          <record>false</record>
        </staticBinding>
        <staticBinding id="f7ab5a7a-ddd0-485e-b30a-4a092d3118a4">
          <annotation></annotation>
          <assignFromContext>false</assignFromContext>
          <assignToContext>false</assignToContext>
          <inputType>STRING</inputType>
          <isList>false</isList>
          <required>false</required>
          <isPersisted>true</isPersisted>
          <inputSymbol>fw_device_ip</inputSymbol>
          <listDelimiter>,</listDelimiter>
          <value>${fw_device_ip}</value>
          <record>false</record>
        </staticBinding>
        <staticBinding id="773cdb6e-28a2-4dde-a257-b5d17080f081">
          <annotation></annotation>
          <assignFromContext>false</assignFromContext>
          <assignToContext>false</assignToContext>
          <inputType>STRING</inputType>
          <isList>false</isList>
          <required>true</required>
          <isPersisted>true</isPersisted>
          <inputSymbol>lb_virtual_server</inputSymbol>
          <listDelimiter>,</listDelimiter>
          <value>${lb_virtual_server}</value>
          <record>false</record>
        </staticBinding>
        <staticBinding id="06210b28-5622-4c8e-92da-a295df46ee97">
          <annotation></annotation>
          <assignFromContext>false</assignFromContext>
          <assignToContext>false</assignToContext>
          <inputType>STRING</inputType>
          <isList>false</isList>
          <required>true</required>
          <isPersisted>true</isPersisted>
          <inputSymbol>lb_port</inputSymbol>
          <listDelimiter>,</listDelimiter>
          <value>${lb_port}</value>
          <record>false</record>
        </staticBinding>
      </bindings>
      <transitions>
        <transition id="cf83ab12-a972-4cda-b167-47ef17c04e84">
          <annotation></annotation>
          <name>failure</name>
          <command>NEXT</command>
          <linkMode>false</linkMode>
          <responseSymbol>failure</responseSymbol>
          <shouldHandoff>false</shouldHandoff>
          <transitionValue>0.0</transitionValue>
          <destination>
            <refId>cee4738e-a1e6-4428-8cbe-fe346ffa630d</refId>
          </destination>
          <source>
            <refId>27e39166-52ef-4977-bc8a-254457c85060</refId>
          </source>
          <positions>
            <point>
              <x>379.0</x>
              <y>340.0</y>
            </point>
            <point>
              <x>165.0</x>
              <y>500.0</y>
            </point>
          </positions>
          <labelPosition>
            <x>333.0</x>
            <y>0.0</y>
          </labelPosition>
        </transition>
        <transition id="4cda852e-84a3-4885-865b-6c728ca111a4">
          <annotation></annotation>
          <name>success</name>
          <command>NEXT</command>
          <linkMode>false</linkMode>
          <responseSymbol>success</responseSymbol>
          <shouldHandoff>false</shouldHandoff>
          <transitionValue>0.0</transitionValue>
          <destination>
            <refId>fe6d117c-63ed-4b9f-a0ee-cd461ff07c28</refId>
          </destination>
          <source>
            <refId>27e39166-52ef-4977-bc8a-254457c85060</refId>
          </source>
          <positions>
            <point>
              <x>379.0</x>
              <y>340.0</y>
            </point>
            <point>
              <x>505.0</x>
              <y>350.0</y>
            </point>
          </positions>
          <labelPosition>
            <x>333.0</x>
            <y>0.0</y>
          </labelPosition>
        </transition>
      </transitions>
      <properties/>
      <opRef>
        <refId>e39bc53d-bfb2-4574-8a41-a616032e1f95</refId>
      </opRef>
      <assignments>
        <flowVariableAssignment id="f914d5fb-22ad-4e93-b586-2ca9488e728c">
          <annotation></annotation>
          <name>assignment</name>
          <action>OVERWRITE</action>
          <assignmentTargetType>FLOW_OUTPUT_FIELD</assignmentTargetType>
          <contextKey>sub_flow_name</contextKey>
          <expression id="0de4f2e6-4a65-48d6-a817-829a044081fb">
            <annotation></annotation>
            <name>Result: sub_flow_name</name>
            <fieldName>sub_flow_name</fieldName>
            <sourceType>AVAILABLE_RESULT</sourceType>
            <filters/>
          </expression>
        </flowVariableAssignment>
        <flowVariableAssignment id="e1d24499-a19a-4bf7-af2b-8762e0541d55">
          <annotation></annotation>
          <name>assignment</name>
          <action>OVERWRITE</action>
          <assignmentTargetType>FLOW_OUTPUT_FIELD</assignmentTargetType>
          <contextKey>step_name</contextKey>
          <expression id="396dd796-ea68-4351-b578-946b945e381d">
            <annotation></annotation>
            <name>Result: step_name</name>
            <fieldName>step_name</fieldName>
            <sourceType>AVAILABLE_RESULT</sourceType>
            <filters/>
          </expression>
        </flowVariableAssignment>
        <flowVariableAssignment id="c14afd41-b8a4-4408-85ab-0f5cda1cc1d0">
          <annotation></annotation>
          <name>assignment</name>
          <action>OVERWRITE</action>
          <assignmentTargetType>FLOW_OUTPUT_FIELD</assignmentTargetType>
          <contextKey>error_message</contextKey>
          <expression id="e28d14c4-d4f1-4839-bc4d-541edddda912">
            <annotation></annotation>
            <name>Result: error_message</name>
            <fieldName>error_message</fieldName>
            <sourceType>AVAILABLE_RESULT</sourceType>
            <filters/>
          </expression>
        </flowVariableAssignment>
      </assignments>
      <throttleSize>0</throttleSize>
    </step>
    <step id="fe6d117c-63ed-4b9f-a0ee-cd461ff07c28">
      <annotation>c29ff47a-4365-444e-bef7-66b10cb1f2ee.fe6d117c-63ed-4b9f-a0ee-cd461ff07c28.description</annotation>
      <name>List Appender</name>
      <bounds>
        <x>455.0</x>
        <y>309.0</y>
      </bounds>
      <layer>-1</layer>
      <hideInbound>false</hideInbound>
      <addResultToRunContext>false</addResultToRunContext>
      <isCriticalStep>false</isCriticalStep>
      <isNonBlocking>false</isNonBlocking>
      <isParallelStep>false</isParallelStep>
      <isSingleResponse>false</isSingleResponse>
      <recordInHistory>false</recordInHistory>
      <recordRawOutput>true</recordRawOutput>
      <recordPrimaryOutput>true</recordPrimaryOutput>
      <checkPointStep>true</checkPointStep>
      <historyCheckPointStep>true</historyCheckPointStep>
      <scriptResultStep>false</scriptResultStep>
      <userPrompt></userPrompt>
      <bindings>
        <staticBinding id="55cd0831-26ee-420f-9264-b319f5cca341">
          <annotation></annotation>
          <assignFromContext>false</assignFromContext>
          <assignToContext>false</assignToContext>
          <inputType>STRING</inputType>
          <isList>false</isList>
          <required>true</required>
          <isPersisted>true</isPersisted>
          <inputSymbol>keyName</inputSymbol>
          <listDelimiter>,</listDelimiter>
          <value>list_of_added_nodes</value>
          <record>false</record>
        </staticBinding>
        <staticBinding id="6ee647ee-5fa4-4730-9ddf-4d2da684b7e7">
          <annotation></annotation>
          <assignFromContext>false</assignFromContext>
          <assignToContext>false</assignToContext>
          <inputType>STRING</inputType>
          <isList>false</isList>
          <required>true</required>
          <isPersisted>true</isPersisted>
          <inputSymbol>resultText</inputSymbol>
          <listDelimiter>,</listDelimiter>
          <value>${node_ip}</value>
          <record>false</record>
        </staticBinding>
        <staticBinding id="3ba11119-051b-4786-95d6-25c4907cfd26">
          <annotation></annotation>
          <assignFromContext>false</assignFromContext>
          <assignToContext>false</assignToContext>
          <inputType>STRING</inputType>
          <isList>false</isList>
          <required>false</required>
          <isPersisted>true</isPersisted>
          <inputSymbol>delimiter</inputSymbol>
          <listDelimiter>,</listDelimiter>
          <value>,</value>
          <record>false</record>
        </staticBinding>
      </bindings>
      <transitions>
        <transition id="c0de2259-8a21-491d-947b-cb12e0d4558b">
          <annotation></annotation>
          <name>success</name>
          <command>NEXT</command>
          <linkMode>false</linkMode>
          <responseSymbol>success</responseSymbol>
          <shouldHandoff>false</shouldHandoff>
          <transitionValue>0.0</transitionValue>
          <destination>
            <refId>d956b6a2-26fc-49b6-8fc1-f8a695a41cac</refId>
          </destination>
          <source>
            <refId>fe6d117c-63ed-4b9f-a0ee-cd461ff07c28</refId>
          </source>
          <positions>
            <point>
              <x>499.7307692307693</x>
              <y>315.0</y>
            </point>
            <point>
              <x>329.0</x>
              <y>149.0</y>
            </point>
          </positions>
          <labelPosition>
            <x>333.0</x>
            <y>0.0</y>
          </labelPosition>
        </transition>
      </transitions>
      <properties/>
      <opRef>
        <refId>f6e6cb22-1802-4fca-9f9b-4c699c486aa6</refId>
      </opRef>
      <assignments/>
      <throttleSize>0</throttleSize>
    </step>
    <step id="e5ce1c98-d890-4e1c-89c4-c2e99fe9c116">
      <annotation>c29ff47a-4365-444e-bef7-66b10cb1f2ee.e5ce1c98-d890-4e1c-89c4-c2e99fe9c116.description</annotation>
      <name>Update lbVirtualServer</name>
      <bounds>
        <x>705.0</x>
        <y>99.0</y>
      </bounds>
      <layer>-1</layer>
      <hideInbound>false</hideInbound>
      <addResultToRunContext>false</addResultToRunContext>
      <isCriticalStep>false</isCriticalStep>
      <isNonBlocking>false</isNonBlocking>
      <isParallelStep>false</isParallelStep>
      <isSingleResponse>false</isSingleResponse>
      <recordInHistory>false</recordInHistory>
      <recordRawOutput>false</recordRawOutput>
      <recordPrimaryOutput>false</recordPrimaryOutput>
      <checkPointStep>true</checkPointStep>
      <historyCheckPointStep>true</historyCheckPointStep>
      <scriptResultStep>false</scriptResultStep>
      <userPrompt></userPrompt>
      <bindings>
        <staticBinding id="71f3ad28-dbb7-4d82-baaf-c96c982ef923">
          <annotation></annotation>
          <assignFromContext>true</assignFromContext>
          <assignToContext>true</assignToContext>
          <inputType>STRING</inputType>
          <isList>false</isList>
          <required>false</required>
          <isPersisted>true</isPersisted>
          <inputSymbol>onlyUpdate</inputSymbol>
          <listDelimiter>,</listDelimiter>
          <value>yes</value>
          <record>false</record>
        </staticBinding>
        <staticBinding id="f6f99efb-ee09-4dd8-9027-e0c7ff13b6db">
          <annotation></annotation>
          <assignFromContext>false</assignFromContext>
          <assignToContext>false</assignToContext>
          <inputType>STRING</inputType>
          <isList>false</isList>
          <required>false</required>
          <isPersisted>true</isPersisted>
          <inputSymbol>displayName</inputSymbol>
          <listDelimiter>,</listDelimiter>
          <value>Nodes</value>
          <record>false</record>
        </staticBinding>
        <staticBinding id="4017b211-af60-489e-8235-e269fac7eafc">
          <annotation></annotation>
          <assignFromContext>false</assignFromContext>
          <assignToContext>false</assignToContext>
          <inputType>STRING</inputType>
          <isList>false</isList>
          <required>false</required>
          <isPersisted>true</isPersisted>
          <inputSymbol>propertyName</inputSymbol>
          <listDelimiter>,</listDelimiter>
          <value>nodeList</value>
          <record>false</record>
        </staticBinding>
        <staticBinding id="c787dd9f-50c4-4ffd-bf3c-cd0c1580d8b8">
          <annotation></annotation>
          <assignFromContext>true</assignFromContext>
          <assignToContext>true</assignToContext>
          <inputType>STRING</inputType>
          <isList>false</isList>
          <required>false</required>
          <isPersisted>true</isPersisted>
          <inputSymbol>valueType</inputSymbol>
          <listDelimiter>,</listDelimiter>
          <value>STRING</value>
          <record>false</record>
        </staticBinding>
        <staticBinding id="593f6f10-6672-411c-bf60-60a29766323f">
          <annotation></annotation>
          <fromContextKey>rule_str</fromContextKey>
          <assignFromContext>false</assignFromContext>
          <assignToContext>false</assignToContext>
          <inputType>STRING</inputType>
          <isList>false</isList>
          <required>false</required>
          <isPersisted>true</isPersisted>
          <inputSymbol>values</inputSymbol>
          <listDelimiter>,</listDelimiter>
          <value>${concat_node_list}</value>
          <record>false</record>
        </staticBinding>
        <staticBinding id="46ba8e33-faac-4424-8b59-f23923dd7195">
          <annotation></annotation>
          <assignFromContext>true</assignFromContext>
          <assignToContext>true</assignToContext>
          <inputType>STRING</inputType>
          <isList>false</isList>
          <required>false</required>
          <isPersisted>true</isPersisted>
          <inputSymbol>separator</inputSymbol>
          <listDelimiter>,</listDelimiter>
          <value>,</value>
          <record>false</record>
        </staticBinding>
        <userInputBinding id="5a64a9ca-0d14-457d-9b14-7ab8f5e0d28e">
          <annotation></annotation>
          <toContextKey>artifact</toContextKey>
          <fromContextKey>artifact</fromContextKey>
          <assignFromContext>true</assignFromContext>
          <assignToContext>true</assignToContext>
          <inputType>STRING</inputType>
          <isList>false</isList>
          <required>true</required>
          <isPersisted>true</isPersisted>
          <inputSymbol>componentId</inputSymbol>
          <listDelimiter>,</listDelimiter>
          <record>false</record>
          <prompt>c29ff47a-4365-444e-bef7-66b10cb1f2ee.5a64a9ca-0d14-457d-9b14-7ab8f5e0d28e.prompt</prompt>
          <isMultiSelect>false</isMultiSelect>
          <sourceDelimiter>|</sourceDelimiter>
        </userInputBinding>
        <userInputBinding id="a155fa06-707c-441e-ae63-f3202da5ccf5">
          <annotation></annotation>
          <assignFromContext>true</assignFromContext>
          <assignToContext>true</assignToContext>
          <inputType>STRING</inputType>
          <isList>false</isList>
          <required>true</required>
          <isPersisted>true</isPersisted>
          <inputSymbol>userIdentifier</inputSymbol>
          <listDelimiter>,</listDelimiter>
          <record>false</record>
          <prompt>c29ff47a-4365-444e-bef7-66b10cb1f2ee.a155fa06-707c-441e-ae63-f3202da5ccf5.prompt</prompt>
          <isMultiSelect>false</isMultiSelect>
          <sourceDelimiter>|</sourceDelimiter>
        </userInputBinding>
      </bindings>
      <transitions>
        <transition id="de0f8e08-7b71-43c2-9768-2f1426763e90">
          <annotation></annotation>
          <name>failure</name>
          <command>NEXT</command>
          <linkMode>false</linkMode>
          <responseSymbol>failure</responseSymbol>
          <shouldHandoff>false</shouldHandoff>
          <transitionValue>0.0</transitionValue>
          <destination>
            <refId>b9205eb5-bfb2-45f8-80d0-9002c45ce869</refId>
          </destination>
          <source>
            <refId>e5ce1c98-d890-4e1c-89c4-c2e99fe9c116</refId>
          </source>
          <positions>
            <point>
              <x>737.0</x>
              <y>122.0</y>
            </point>
            <point>
              <x>907.0</x>
              <y>316.0</y>
            </point>
          </positions>
          <labelPosition>
            <x>333.0</x>
            <y>0.0</y>
          </labelPosition>
        </transition>
        <transition id="3d63e5cc-6c10-4ad7-b676-eda29bd47aa8">
          <annotation></annotation>
          <name>success</name>
          <command>NEXT</command>
          <linkMode>false</linkMode>
          <responseSymbol>success</responseSymbol>
          <shouldHandoff>false</shouldHandoff>
          <transitionValue>0.0</transitionValue>
          <destination>
            <refId>71f76481-e300-469b-a14a-7d4bbd8132a4</refId>
          </destination>
          <source>
            <refId>e5ce1c98-d890-4e1c-89c4-c2e99fe9c116</refId>
          </source>
          <positions>
            <point>
              <x>737.0</x>
              <y>133.0</y>
            </point>
            <point>
              <x>930.0</x>
              <y>133.0</y>
            </point>
          </positions>
          <labelPosition>
            <x>333.0</x>
            <y>0.0</y>
          </labelPosition>
        </transition>
      </transitions>
      <properties/>
      <opRef>
        <refId>fe69637d-9835-4aea-912f-844b4bc189bf</refId>
      </opRef>
      <assignments/>
      <throttleSize>0</throttleSize>
    </step>
    <step id="28dfc56b-4479-498b-bd88-62f2fd5d1263">
      <annotation></annotation>
      <name>F5_Save_config</name>
      <bounds>
        <x>575.0</x>
        <y>99.0</y>
      </bounds>
      <layer>-1</layer>
      <hideInbound>false</hideInbound>
      <addResultToRunContext>false</addResultToRunContext>
      <isCriticalStep>false</isCriticalStep>
      <isNonBlocking>false</isNonBlocking>
      <isParallelStep>false</isParallelStep>
      <isSingleResponse>false</isSingleResponse>
      <recordInHistory>false</recordInHistory>
      <recordRawOutput>true</recordRawOutput>
      <recordPrimaryOutput>true</recordPrimaryOutput>
      <checkPointStep>true</checkPointStep>
      <historyCheckPointStep>true</historyCheckPointStep>
      <scriptResultStep>false</scriptResultStep>
      <userPrompt></userPrompt>
      <bindings>
        <staticBinding id="01f2d22f-42ab-4567-8535-1e93d3b81931">
          <annotation></annotation>
          <assignFromContext>false</assignFromContext>
          <assignToContext>false</assignToContext>
          <inputType>STRING</inputType>
          <isList>false</isList>
          <required>false</required>
          <isPersisted>true</isPersisted>
          <inputSymbol>na_hostname</inputSymbol>
          <listDelimiter>,</listDelimiter>
          <value>${na_hostname}</value>
          <record>false</record>
        </staticBinding>
        <staticBinding id="f29e43eb-ade4-41e9-a137-569a085c3faa">
          <annotation></annotation>
          <assignFromContext>false</assignFromContext>
          <assignToContext>false</assignToContext>
          <inputType>STRING</inputType>
          <isList>false</isList>
          <required>false</required>
          <isPersisted>true</isPersisted>
          <inputSymbol>na_port</inputSymbol>
          <listDelimiter>,</listDelimiter>
          <value>${na_port}</value>
          <record>false</record>
        </staticBinding>
        <staticBinding id="c917faf0-bb58-4542-8921-8a2929c08e8e">
          <annotation></annotation>
          <assignFromContext>false</assignFromContext>
          <assignToContext>false</assignToContext>
          <inputType>STRING</inputType>
          <isList>false</isList>
          <required>false</required>
          <isPersisted>true</isPersisted>
          <inputSymbol>na_protocol</inputSymbol>
          <listDelimiter>,</listDelimiter>
          <value>${na_protocol}</value>
          <record>false</record>
        </staticBinding>
        <staticBinding id="baedc9db-b701-4fb3-ad51-70af52745ce3">
          <annotation></annotation>
          <assignFromContext>false</assignFromContext>
          <assignToContext>false</assignToContext>
          <inputType>STRING</inputType>
          <isList>false</isList>
          <required>false</required>
          <isPersisted>true</isPersisted>
          <inputSymbol>na_user</inputSymbol>
          <listDelimiter>,</listDelimiter>
          <value>${na_user}</value>
          <record>false</record>
        </staticBinding>
        <staticBinding id="5715d951-db80-4abb-b12a-fca5ab017dbb">
          <annotation></annotation>
          <assignFromContext>false</assignFromContext>
          <assignToContext>false</assignToContext>
          <inputType>STRING</inputType>
          <isList>false</isList>
          <required>false</required>
          <isPersisted>true</isPersisted>
          <inputSymbol>na_password</inputSymbol>
          <listDelimiter>,</listDelimiter>
          <value>${na_password}</value>
          <record>false</record>
        </staticBinding>
        <staticBinding id="761b6621-798f-440a-8d64-c94e5090ffa0">
          <annotation></annotation>
          <assignFromContext>false</assignFromContext>
          <assignToContext>false</assignToContext>
          <inputType>STRING</inputType>
          <isList>false</isList>
          <required>false</required>
          <isPersisted>true</isPersisted>
          <inputSymbol>fw_device_ip</inputSymbol>
          <listDelimiter>,</listDelimiter>
          <value>${fw_device_ip}</value>
          <record>false</record>
        </staticBinding>
      </bindings>
      <transitions>
        <transition id="1e41662c-6f29-4368-8dbb-fc3c2c4db4dd">
          <annotation></annotation>
          <name>success</name>
          <command>NEXT</command>
          <linkMode>false</linkMode>
          <responseSymbol>success</responseSymbol>
          <shouldHandoff>false</shouldHandoff>
          <transitionValue>0.0</transitionValue>
          <destination>
            <refId>e5ce1c98-d890-4e1c-89c4-c2e99fe9c116</refId>
          </destination>
          <source>
            <refId>28dfc56b-4479-498b-bd88-62f2fd5d1263</refId>
          </source>
          <positions>
            <point>
              <x>625.0</x>
              <y>131.0</y>
            </point>
            <point>
              <x>737.0</x>
              <y>133.0</y>
            </point>
          </positions>
          <labelPosition>
            <x>333.0</x>
            <y>0.0</y>
          </labelPosition>
        </transition>
        <transition id="afc7cb8b-1a49-4700-ae18-4abac5227d1d">
          <annotation></annotation>
          <name>failure</name>
          <command>NEXT</command>
          <linkMode>false</linkMode>
          <responseSymbol>failure</responseSymbol>
          <shouldHandoff>false</shouldHandoff>
          <transitionValue>0.0</transitionValue>
          <destination>
            <refId>b9205eb5-bfb2-45f8-80d0-9002c45ce869</refId>
          </destination>
          <source>
            <refId>28dfc56b-4479-498b-bd88-62f2fd5d1263</refId>
          </source>
          <positions>
            <point>
              <x>625.0</x>
              <y>131.0</y>
            </point>
            <point>
              <x>907.0</x>
              <y>316.0</y>
            </point>
          </positions>
          <labelPosition>
            <x>333.0</x>
            <y>0.0</y>
          </labelPosition>
        </transition>
      </transitions>
      <properties/>
      <opRef>
        <refId>0e9b2c0e-36f1-4843-b945-d60149bce378</refId>
      </opRef>
      <assignments/>
      <throttleSize>0</throttleSize>
    </step>
    <step id="0f8e30ea-773f-4da7-b1ce-3bbc7c92849b">
      <annotation>c29ff47a-4365-444e-bef7-66b10cb1f2ee.0f8e30ea-773f-4da7-b1ce-3bbc7c92849b.description</annotation>
      <name>Do Nothing</name>
      <bounds>
        <x>440.0</x>
        <y>99.0</y>
      </bounds>
      <layer>-1</layer>
      <hideInbound>false</hideInbound>
      <addResultToRunContext>false</addResultToRunContext>
      <isCriticalStep>false</isCriticalStep>
      <isNonBlocking>false</isNonBlocking>
      <isParallelStep>false</isParallelStep>
      <isSingleResponse>false</isSingleResponse>
      <recordInHistory>false</recordInHistory>
      <recordRawOutput>true</recordRawOutput>
      <recordPrimaryOutput>true</recordPrimaryOutput>
      <checkPointStep>true</checkPointStep>
      <historyCheckPointStep>true</historyCheckPointStep>
      <scriptResultStep>false</scriptResultStep>
      <userPrompt></userPrompt>
      <bindings>
        <staticBinding id="b1d15b55-5ea1-43be-a8f0-03d1514bb425">
          <annotation></annotation>
          <assignFromContext>false</assignFromContext>
          <assignToContext>false</assignToContext>
          <inputType>STRING</inputType>
          <isList>false</isList>
          <required>false</required>
          <isPersisted>true</isPersisted>
          <inputSymbol>field1</inputSymbol>
          <listDelimiter>,</listDelimiter>
          <record>false</record>
        </staticBinding>
        <staticBinding id="b6ac4f7a-1acf-4593-8197-caa1b33f6806">
          <annotation></annotation>
          <assignFromContext>false</assignFromContext>
          <assignToContext>false</assignToContext>
          <inputType>STRING</inputType>
          <isList>false</isList>
          <required>false</required>
          <isPersisted>true</isPersisted>
          <inputSymbol>field2</inputSymbol>
          <listDelimiter>,</listDelimiter>
          <record>false</record>
        </staticBinding>
        <staticBinding id="11a29b4a-06a1-4067-9afd-52b104cda938">
          <annotation></annotation>
          <assignFromContext>false</assignFromContext>
          <assignToContext>false</assignToContext>
          <inputType>STRING</inputType>
          <isList>false</isList>
          <required>false</required>
          <isPersisted>true</isPersisted>
          <inputSymbol>field3</inputSymbol>
          <listDelimiter>,</listDelimiter>
          <record>false</record>
        </staticBinding>
        <staticBinding id="9b697b79-2282-42b0-a796-0e959e175df1">
          <annotation></annotation>
          <assignFromContext>false</assignFromContext>
          <assignToContext>false</assignToContext>
          <inputType>STRING</inputType>
          <isList>false</isList>
          <required>false</required>
          <isPersisted>true</isPersisted>
          <inputSymbol>field4</inputSymbol>
          <listDelimiter>,</listDelimiter>
          <record>false</record>
        </staticBinding>
      </bindings>
      <transitions>
        <transition id="4360afe0-f974-42d3-9530-7220bff15330">
          <annotation></annotation>
          <name>success</name>
          <command>NEXT</command>
          <linkMode>false</linkMode>
          <responseSymbol>success</responseSymbol>
          <shouldHandoff>false</shouldHandoff>
          <transitionValue>0.0</transitionValue>
          <destination>
            <refId>28dfc56b-4479-498b-bd88-62f2fd5d1263</refId>
          </destination>
          <source>
            <refId>0f8e30ea-773f-4da7-b1ce-3bbc7c92849b</refId>
          </source>
          <positions>
            <point>
              <x>490.0</x>
              <y>133.0</y>
            </point>
            <point>
              <x>638.0</x>
              <y>184.0</y>
            </point>
          </positions>
          <labelPosition>
            <x>333.0</x>
            <y>0.0</y>
          </labelPosition>
        </transition>
      </transitions>
      <properties/>
      <opRef>
        <refId>ddd79f22-8b1e-4605-88d5-d912bb2da2b9</refId>
      </opRef>
      <assignments>
        <flowVariableAssignment id="a726ebac-61a5-416d-bfad-bc423d64e80a">
          <annotation></annotation>
          <name>assignment</name>
          <action>OVERWRITE</action>
          <assignmentTargetType>FLOW_VARIABLE</assignmentTargetType>
          <contextKey>concat_node_list</contextKey>
          <expression id="0bb831ca-feab-4b7f-afed-c8eec59b8886">
            <annotation></annotation>
            <name>Result Field: Field_1</name>
            <fieldName>Field_1</fieldName>
            <sourceType>RAWRESULT</sourceType>
            <filters>
              <concat id="4d9b4a47-6ce5-4ae4-8991-1a784a97fa80">
                <annotation></annotation>
                <name>Format</name>
                <text>${node_list},${list_of_added_nodes}</text>
                <position>END</position>
              </concat>
            </filters>
          </expression>
        </flowVariableAssignment>
      </assignments>
      <throttleSize>0</throttleSize>
    </step>
  </steps>
  <startSteps>af134ceb-8553-42ce-bef9-4ea19d8167d0</startSteps>
</flow>