<?xml version="1.0" encoding="UTF-8"?>
<flow id="05d7ad2d-d9b4-47d5-aa62-c1ffcd689a93">
  <descriptionCdata><![CDATA[05d7ad2d-d9b4-47d5-aa62-c1ffcd689a93.20837ab0-df79-4eec-911a-78100c4d02c6.description=<pre>\nUse this template when you are creating a new flow. You should remove the Success or Failure step.\n\nResponses\:\n    success - the flow completed successfully.\n    failure - the flow completed unsuccessfully.\n</pre>
05d7ad2d-d9b4-47d5-aa62-c1ffcd689a93.2e5cf52a-90e6-41a6-b8f2-be43410eb180.description=<pre>\nUse this template when you are creating a new flow. You should remove the Success or Failure step.\n\nResponses\:\n    success - the flow completed successfully.\n    failure - the flow completed unsuccessfully.\n</pre>
05d7ad2d-d9b4-47d5-aa62-c1ffcd689a93.52e82b38-15ea-46e8-9147-740162ca2e9a.description=<pre>\nSend SMS Messages \nThis operation sends an SMS message \nSMS messages are sent/received using the Twilio service. \n\nFor details, see\: https\://www.twilio.com/  \n\n\n\n Inputs\: \n\t accountSid - Get your Account Sid and Token at twilio.com/user/account\n\t authenticationToken - Get your Account Sid and Token at twilio.com/user/account\n\t from - Message will be sent from this Twillo number\n\t\t Format\: internationally-standardized format for all phone numbers, E.164 number formatting [http\://en.wikipedia.org/wiki/E.164]\n\t\t\t [+][country code][subscriber number including area code] for example\: +14804055101\n\t\t\t https\://www.twilio.com/help/faq/phone-numbers/how-do-i-format-phone-numbers-to-work-internationally\n\t to - Message will be sent to this number\n\t\t Format - same as "from"\t \n\t textMessage - The SMS text message\n\t mediaURL - The URL of the media you wish to send out with the message. gif, png and jpeg such as\: http\://www.example.org/image.jpg\n\n\nOutputs\: \n\t returnResult\n\t returnCode\n\t errorMessage\n\t errorCode\n\t status\n\t sid\n\t price\n\t priceUnit\t \n\t direction\n\t dateCreated\n\n\nNotes\: \n\t Twilio note\: For the 3rd party Twillo error message explanations use the Twilio URL\: https\://www.twilio.com/docs/errors/[error_code] \n\t For example\: https\://www.twilio.com/docs/errors/21612 \n\t Twilio sdk version\: [twilio-java-sdk\=3.4.5]\n \t Twilio security note\: https\://www.twilio.com/docs/security \n </pre>
05d7ad2d-d9b4-47d5-aa62-c1ffcd689a93.e5131818-9739-4524-918d-afb7ee389f72.description=<pre>\nUse this template when you are creating a new flow. You should remove the Success or Failure step.\n\nResponses\:\n    success - the flow completed successfully.\n    failure - the flow completed unsuccessfully.\n</pre>
]]></descriptionCdata>
  <annotation></annotation>
  <name>Par splt</name>
  <categories/>
  <inputs/>
  <possibleResponses>
    <opResponse id="e4229f1d-4245-4eab-9839-c45654470567">
      <annotation></annotation>
      <name>failure</name>
      <isDefault>false</isDefault>
      <onFailure>true</onFailure>
      <type>ERROR</type>
      <matchRules/>
    </opResponse>
    <opResponse id="5e9b0484-fbbd-418e-8e68-3592ec9a5ab7">
      <annotation></annotation>
      <name>success</name>
      <isDefault>true</isDefault>
      <onFailure>false</onFailure>
      <type>RESOLVED</type>
      <matchRules/>
    </opResponse>
  </possibleResponses>
  <availableResultExpressions/>
  <resultExpression id="3584d4f4-696f-4e3b-b619-2a3e865c9753">
    <annotation></annotation>
    <name>FailureMessage</name>
    <fieldName>FailureMessage</fieldName>
    <sourceType>RAWRESULT</sourceType>
    <filters/>
  </resultExpression>
  <iconSpec id="f77c52b7-e38e-4caf-b519-b7beed7d6080">
    <baseIcon>flow.png</baseIcon>
    <basePath>System</basePath>
    <readOnly>false</readOnly>
    <layers/>
  </iconSpec>
  <callouts/>
  <checkPointFlow>true</checkPointFlow>
  <compatibleRuntimeContext>false</compatibleRuntimeContext>
  <historyCheckPointFlow>true</historyCheckPointFlow>
  <steps>
    <step id="2e5cf52a-90e6-41a6-b8f2-be43410eb180">
      <annotation>05d7ad2d-d9b4-47d5-aa62-c1ffcd689a93.2e5cf52a-90e6-41a6-b8f2-be43410eb180.description</annotation>
      <name>Blank Flow</name>
      <bounds>
        <x>28.0</x>
        <y>134.0</y>
      </bounds>
      <layer>-1</layer>
      <hideInbound>false</hideInbound>
      <addResultToRunContext>false</addResultToRunContext>
      <isCriticalStep>false</isCriticalStep>
      <isNonBlocking>false</isNonBlocking>
      <isParallelStep>false</isParallelStep>
      <isSingleResponse>false</isSingleResponse>
      <recordInHistory>false</recordInHistory>
      <recordRawOutput>true</recordRawOutput>
      <recordPrimaryOutput>true</recordPrimaryOutput>
      <checkPointStep>true</checkPointStep>
      <historyCheckPointStep>true</historyCheckPointStep>
      <scriptResultStep>false</scriptResultStep>
      <userPrompt></userPrompt>
      <bindings/>
      <transitions>
        <transition id="1a419c91-32de-4d94-adba-412c43baf643">
          <annotation></annotation>
          <name>success</name>
          <command>NEXT</command>
          <linkMode>false</linkMode>
          <responseSymbol>success</responseSymbol>
          <shouldHandoff>false</shouldHandoff>
          <transitionValue>0.0</transitionValue>
          <destination>
            <refId>fc093a34-07ff-4b9c-8bd7-4592c0291379</refId>
          </destination>
          <source>
            <refId>2e5cf52a-90e6-41a6-b8f2-be43410eb180</refId>
          </source>
          <positions>
            <point>
              <x>188.0</x>
              <y>270.0</y>
            </point>
            <point>
              <x>464.0</x>
              <y>318.0</y>
            </point>
          </positions>
          <labelPosition>
            <x>333.0</x>
            <y>0.0</y>
          </labelPosition>
        </transition>
        <transition id="4ee82770-7ebb-49c5-9219-b102301f23d4">
          <annotation></annotation>
          <name>failure</name>
          <command>NEXT</command>
          <linkMode>false</linkMode>
          <responseSymbol>failure</responseSymbol>
          <shouldHandoff>false</shouldHandoff>
          <transitionValue>0.0</transitionValue>
          <destination>
            <refId>628ee2f1-c429-4706-a0fd-3b11b76e8e78</refId>
          </destination>
          <source>
            <refId>2e5cf52a-90e6-41a6-b8f2-be43410eb180</refId>
          </source>
          <positions>
            <point>
              <x>188.0</x>
              <y>270.0</y>
            </point>
            <point>
              <x>463.0</x>
              <y>513.0</y>
            </point>
          </positions>
          <labelPosition>
            <x>333.0</x>
            <y>0.0</y>
          </labelPosition>
        </transition>
      </transitions>
      <properties/>
      <opRef>
        <refId>6671d708-26be-4ca2-887b-4adbb9550a01</refId>
      </opRef>
      <assignments/>
      <throttleSize>0</throttleSize>
    </step>
    <parallelMultiStep id="fc093a34-07ff-4b9c-8bd7-4592c0291379">
      <annotation></annotation>
      <name>Multi Lane</name>
      <bounds>
        <x>304.0</x>
        <y>6.0</y>
      </bounds>
      <layer>-1</layer>
      <hideInbound>false</hideInbound>
      <addResultToRunContext>false</addResultToRunContext>
      <isCriticalStep>false</isCriticalStep>
      <isNonBlocking>false</isNonBlocking>
      <isParallelStep>false</isParallelStep>
      <isSingleResponse>true</isSingleResponse>
      <recordInHistory>false</recordInHistory>
      <recordRawOutput>true</recordRawOutput>
      <recordPrimaryOutput>true</recordPrimaryOutput>
      <checkPointStep>true</checkPointStep>
      <historyCheckPointStep>true</historyCheckPointStep>
      <scriptResultStep>false</scriptResultStep>
      <userPrompt></userPrompt>
      <bindings/>
      <transitions>
        <transition id="984ea344-89b4-4bba-85f6-bb1bf0ea6c9c">
          <annotation></annotation>
          <name>done</name>
          <command>NEXT</command>
          <linkMode>false</linkMode>
          <responseSymbol>done</responseSymbol>
          <shouldHandoff>false</shouldHandoff>
          <transitionValue>0.0</transitionValue>
          <destination>
            <refId>c30b9644-2612-4cba-b3b5-4f151efda62b</refId>
          </destination>
          <source>
            <refId>fc093a34-07ff-4b9c-8bd7-4592c0291379</refId>
          </source>
          <positions>
            <point>
              <x>354.0</x>
              <y>42.0</y>
            </point>
            <point>
              <x>832.0</x>
              <y>175.0</y>
            </point>
          </positions>
          <labelPosition>
            <x>333.0</x>
            <y>0.0</y>
          </labelPosition>
        </transition>
      </transitions>
      <properties/>
      <doneResponse>
        <refId>b8619f25-c4c1-488f-a5c8-3b0583245c5c</refId>
      </doneResponse>
      <steps>
        <step id="52e82b38-15ea-46e8-9147-740162ca2e9a">
          <annotation>05d7ad2d-d9b4-47d5-aa62-c1ffcd689a93.52e82b38-15ea-46e8-9147-740162ca2e9a.description</annotation>
          <name>Send SMS</name>
          <bounds>
            <x>432.0</x>
            <y>73.0</y>
          </bounds>
          <layer>-1</layer>
          <hideInbound>false</hideInbound>
          <addResultToRunContext>false</addResultToRunContext>
          <isCriticalStep>false</isCriticalStep>
          <isNonBlocking>false</isNonBlocking>
          <isParallelStep>false</isParallelStep>
          <isSingleResponse>false</isSingleResponse>
          <recordInHistory>false</recordInHistory>
          <recordRawOutput>true</recordRawOutput>
          <recordPrimaryOutput>true</recordPrimaryOutput>
          <checkPointStep>true</checkPointStep>
          <historyCheckPointStep>true</historyCheckPointStep>
          <scriptResultStep>false</scriptResultStep>
          <userPrompt></userPrompt>
          <bindings>
            <staticBinding id="1b3ac846-0da2-44d2-8fae-add7a15f1f21">
              <annotation>Get your Account Sid and Token at twilio.com/user/account</annotation>
              <assignFromContext>false</assignFromContext>
              <assignToContext>false</assignToContext>
              <inputType>STRING</inputType>
              <isList>false</isList>
              <required>true</required>
              <isPersisted>true</isPersisted>
              <inputSymbol>accountSid</inputSymbol>
              <listDelimiter>,</listDelimiter>
              <value>AC673965ed662ca95f9df0b74a02192a61</value>
              <record>false</record>
            </staticBinding>
            <staticBinding id="aa23f9f8-07fd-4663-ab4e-ef8a62a81080">
              <annotation>Get your Account Sid and Token at twilio.com/user/account</annotation>
              <assignFromContext>false</assignFromContext>
              <assignToContext>false</assignToContext>
              <inputType>ENCRYPTED</inputType>
              <isList>false</isList>
              <required>true</required>
              <isPersisted>true</isPersisted>
              <inputSymbol>authenticationToken</inputSymbol>
              <listDelimiter>,</listDelimiter>
              <value>{OBFUSCATED}kdEIajW6fhSM9IH4pf/4VxoYwrOA1VOLqtgXovPvYkm0VDamdZgpAIYuef/ks/Og</value>
              <record>false</record>
            </staticBinding>
            <staticBinding id="86fc254f-ee63-49b0-b0fd-f1656aa9d938">
              <annotation>Message will be sent from this Twillo number</annotation>
              <assignFromContext>false</assignFromContext>
              <assignToContext>false</assignToContext>
              <inputType>STRING</inputType>
              <isList>false</isList>
              <required>true</required>
              <isPersisted>true</isPersisted>
              <inputSymbol>from</inputSymbol>
              <listDelimiter>,</listDelimiter>
              <value>+16154578396</value>
              <record>false</record>
            </staticBinding>
            <staticBinding id="954d534f-e350-473c-8772-d69b30e5385f">
              <annotation>Message will be sent to this number</annotation>
              <assignFromContext>false</assignFromContext>
              <assignToContext>false</assignToContext>
              <inputType>STRING</inputType>
              <isList>false</isList>
              <required>true</required>
              <isPersisted>true</isPersisted>
              <inputSymbol>to</inputSymbol>
              <listDelimiter>,</listDelimiter>
              <value>+17182880535</value>
              <record>false</record>
            </staticBinding>
            <staticBinding id="6db36eaf-c743-4b6b-8069-754d3ec99eb4">
              <annotation>The SMS text message</annotation>
              <assignFromContext>false</assignFromContext>
              <assignToContext>false</assignToContext>
              <inputType>STRING</inputType>
              <isList>false</isList>
              <required>true</required>
              <isPersisted>true</isPersisted>
              <inputSymbol>textMessage</inputSymbol>
              <listDelimiter>,</listDelimiter>
              <value>Hey test Twilio</value>
              <record>false</record>
            </staticBinding>
            <staticBinding id="7f3c5e56-cdf3-4d5e-b9f9-0e8e394ed7d7">
              <annotation>The URL of the media you wish to send out with the message. gif , png and jpeg such as: http://www.example.org/image.jpg</annotation>
              <assignFromContext>false</assignFromContext>
              <assignToContext>false</assignToContext>
              <inputType>STRING</inputType>
              <isList>false</isList>
              <required>false</required>
              <isPersisted>true</isPersisted>
              <inputSymbol>mediaURL</inputSymbol>
              <listDelimiter>,</listDelimiter>
              <record>false</record>
            </staticBinding>
          </bindings>
          <transitions>
            <transition id="cb6af99b-4a01-4af4-980b-b6a064c4e061">
              <annotation></annotation>
              <name>failure</name>
              <command>NEXT</command>
              <linkMode>false</linkMode>
              <responseSymbol>failure</responseSymbol>
              <shouldHandoff>false</shouldHandoff>
              <transitionValue>0.0</transitionValue>
              <destination>
                <refId>b8619f25-c4c1-488f-a5c8-3b0583245c5c</refId>
              </destination>
              <source>
                <refId>52e82b38-15ea-46e8-9147-740162ca2e9a</refId>
              </source>
              <positions>
                <point>
                  <x>598.0</x>
                  <y>221.0</y>
                </point>
                <point>
                  <x>754.0</x>
                  <y>256.0</y>
                </point>
              </positions>
              <labelPosition>
                <x>333.0</x>
                <y>0.0</y>
              </labelPosition>
            </transition>
            <transition id="f9ff3e93-bf9b-4e15-bba9-6c1a932b441b">
              <annotation></annotation>
              <name>success</name>
              <command>NEXT</command>
              <linkMode>false</linkMode>
              <responseSymbol>success</responseSymbol>
              <shouldHandoff>false</shouldHandoff>
              <transitionValue>0.0</transitionValue>
              <destination>
                <refId>b8619f25-c4c1-488f-a5c8-3b0583245c5c</refId>
              </destination>
              <source>
                <refId>52e82b38-15ea-46e8-9147-740162ca2e9a</refId>
              </source>
              <positions>
                <point>
                  <x>482.0</x>
                  <y>109.0</y>
                </point>
                <point>
                  <x>542.1531749618589</x>
                  <y>131.6291603999812</y>
                </point>
                <point>
                  <x>584.155461133379</x>
                  <y>131.36988702855206</y>
                </point>
                <point>
                  <x>644.0</x>
                  <y>108.0</y>
                </point>
              </positions>
              <labelPosition>
                <x>333.0</x>
                <y>0.0</y>
              </labelPosition>
            </transition>
          </transitions>
          <properties/>
          <opRef>
            <refId>36853aa0-0daf-4842-8b8a-3769a2417af4</refId>
          </opRef>
          <assignments/>
          <throttleSize>0</throttleSize>
        </step>
        <step id="e5131818-9739-4524-918d-afb7ee389f72">
          <annotation>05d7ad2d-d9b4-47d5-aa62-c1ffcd689a93.e5131818-9739-4524-918d-afb7ee389f72.description</annotation>
          <name>Blank Flow</name>
          <bounds>
            <x>476.0</x>
            <y>220.0</y>
          </bounds>
          <layer>-1</layer>
          <hideInbound>false</hideInbound>
          <addResultToRunContext>false</addResultToRunContext>
          <isCriticalStep>false</isCriticalStep>
          <isNonBlocking>false</isNonBlocking>
          <isParallelStep>false</isParallelStep>
          <isSingleResponse>false</isSingleResponse>
          <recordInHistory>false</recordInHistory>
          <recordRawOutput>true</recordRawOutput>
          <recordPrimaryOutput>true</recordPrimaryOutput>
          <checkPointStep>true</checkPointStep>
          <historyCheckPointStep>true</historyCheckPointStep>
          <scriptResultStep>false</scriptResultStep>
          <userPrompt></userPrompt>
          <bindings/>
          <transitions>
            <transition id="ea3766ae-5f5f-4abf-ac04-7442b84b4640">
              <annotation></annotation>
              <name>failure</name>
              <command>NEXT</command>
              <linkMode>false</linkMode>
              <responseSymbol>failure</responseSymbol>
              <shouldHandoff>false</shouldHandoff>
              <transitionValue>0.0</transitionValue>
              <destination>
                <refId>b8619f25-c4c1-488f-a5c8-3b0583245c5c</refId>
              </destination>
              <source>
                <refId>e5131818-9739-4524-918d-afb7ee389f72</refId>
              </source>
              <positions>
                <point>
                  <x>616.0</x>
                  <y>347.0</y>
                </point>
                <point>
                  <x>754.0</x>
                  <y>400.0</y>
                </point>
              </positions>
              <labelPosition>
                <x>333.0</x>
                <y>0.0</y>
              </labelPosition>
            </transition>
            <transition id="bcdf0741-4583-45a5-8f23-a4cd99f3c6b1">
              <annotation></annotation>
              <name>success</name>
              <command>NEXT</command>
              <linkMode>false</linkMode>
              <responseSymbol>success</responseSymbol>
              <shouldHandoff>false</shouldHandoff>
              <transitionValue>0.0</transitionValue>
              <destination>
                <refId>b8619f25-c4c1-488f-a5c8-3b0583245c5c</refId>
              </destination>
              <source>
                <refId>e5131818-9739-4524-918d-afb7ee389f72</refId>
              </source>
              <positions>
                <point>
                  <x>526.0</x>
                  <y>256.0</y>
                </point>
                <point>
                  <x>585.846971141644</x>
                  <y>276.98564867849586</y>
                </point>
                <point>
                  <x>644.0</x>
                  <y>252.0</y>
                </point>
              </positions>
              <labelPosition>
                <x>333.0</x>
                <y>0.0</y>
              </labelPosition>
            </transition>
          </transitions>
          <properties/>
          <opRef>
            <refId>6671d708-26be-4ca2-887b-4adbb9550a01</refId>
          </opRef>
          <assignments/>
          <throttleSize>0</throttleSize>
        </step>
        <endBranchStep id="b8619f25-c4c1-488f-a5c8-3b0583245c5c">
          <annotation></annotation>
          <name>Resolved : success</name>
          <bounds>
            <x>0.0</x>
            <y>0.0</y>
          </bounds>
          <layer>-1</layer>
          <hideInbound>false</hideInbound>
          <addResultToRunContext>false</addResultToRunContext>
          <isCriticalStep>false</isCriticalStep>
          <isNonBlocking>false</isNonBlocking>
          <isParallelStep>false</isParallelStep>
          <isSingleResponse>false</isSingleResponse>
          <recordInHistory>false</recordInHistory>
          <recordRawOutput>true</recordRawOutput>
          <recordPrimaryOutput>true</recordPrimaryOutput>
          <checkPointStep>true</checkPointStep>
          <historyCheckPointStep>true</historyCheckPointStep>
          <scriptResultStep>false</scriptResultStep>
          <userPrompt></userPrompt>
          <bindings/>
          <transitions>
            <transition id="a1bedc40-6cdb-43f1-9262-18b8c8e5398e">
              <annotation></annotation>
              <name>return</name>
              <command>NEXT</command>
              <linkMode>false</linkMode>
              <responseSymbol>success</responseSymbol>
              <shouldHandoff>false</shouldHandoff>
              <transitionValue>0.0</transitionValue>
              <destination>
                <refId>b8619f25-c4c1-488f-a5c8-3b0583245c5c</refId>
              </destination>
              <source>
                <refId>b8619f25-c4c1-488f-a5c8-3b0583245c5c</refId>
              </source>
              <positions/>
            </transition>
          </transitions>
          <properties/>
        </endBranchStep>
      </steps>
      <startSteps>
        <refId>52e82b38-15ea-46e8-9147-740162ca2e9a</refId>
        <refId>e5131818-9739-4524-918d-afb7ee389f72</refId>
      </startSteps>
      <lanes>
        <parallelLane id="25580ff3-9b92-4e4d-afa7-de89db0592eb">
          <annotation></annotation>
          <name>Semd SMS Message</name>
          <bounds>
            <x>0.0</x>
            <y>0.0</y>
            <width>240.0</width>
            <height>140.0</height>
          </bounds>
          <parallelSteps>
            <refId>52e82b38-15ea-46e8-9147-740162ca2e9a</refId>
          </parallelSteps>
          <parallelStartStep>
            <refId>52e82b38-15ea-46e8-9147-740162ca2e9a</refId>
          </parallelStartStep>
        </parallelLane>
        <parallelLane id="957aa5f8-0b2d-46a4-90cc-250c48b4c01a">
          <annotation></annotation>
          <name>Lane 2</name>
          <bounds>
            <x>0.0</x>
            <y>0.0</y>
            <width>240.0</width>
            <height>140.0</height>
          </bounds>
          <parallelSteps>
            <refId>e5131818-9739-4524-918d-afb7ee389f72</refId>
          </parallelSteps>
          <parallelStartStep>
            <refId>e5131818-9739-4524-918d-afb7ee389f72</refId>
          </parallelStartStep>
        </parallelLane>
        <parallelLane id="238736b4-2034-4dfd-9400-20d27cee086b">
          <annotation></annotation>
          <name>Lane 3</name>
          <bounds>
            <x>0.0</x>
            <y>0.0</y>
            <width>240.0</width>
            <height>140.0</height>
          </bounds>
          <parallelSteps/>
        </parallelLane>
      </lanes>
      <callouts/>
    </parallelMultiStep>
    <returnStep id="628ee2f1-c429-4706-a0fd-3b11b76e8e78">
      <annotation></annotation>
      <name>Error : failure</name>
      <bounds>
        <x>28.0</x>
        <y>270.0</y>
      </bounds>
      <layer>-1</layer>
      <hideInbound>false</hideInbound>
      <addResultToRunContext>false</addResultToRunContext>
      <isCriticalStep>false</isCriticalStep>
      <isNonBlocking>false</isNonBlocking>
      <isParallelStep>false</isParallelStep>
      <isSingleResponse>false</isSingleResponse>
      <recordInHistory>false</recordInHistory>
      <recordRawOutput>true</recordRawOutput>
      <recordPrimaryOutput>true</recordPrimaryOutput>
      <checkPointStep>true</checkPointStep>
      <historyCheckPointStep>true</historyCheckPointStep>
      <scriptResultStep>false</scriptResultStep>
      <userPrompt></userPrompt>
      <bindings/>
      <transitions>
        <transition id="93d841d6-2659-4885-bb46-beaf6f44b9dc">
          <annotation></annotation>
          <name>return</name>
          <command>NEXT</command>
          <linkMode>false</linkMode>
          <responseSymbol>failure</responseSymbol>
          <shouldHandoff>false</shouldHandoff>
          <transitionValue>0.0</transitionValue>
          <destination>
            <refId>628ee2f1-c429-4706-a0fd-3b11b76e8e78</refId>
          </destination>
          <source>
            <refId>628ee2f1-c429-4706-a0fd-3b11b76e8e78</refId>
          </source>
          <positions/>
        </transition>
      </transitions>
      <properties/>
      <returnStepType>ERROR</returnStepType>
      <assignments/>
    </returnStep>
    <multiInstanceStep id="c30b9644-2612-4cba-b3b5-4f151efda62b">
      <annotation></annotation>
      <name>Multi Instance</name>
      <bounds>
        <x>782.0</x>
        <y>82.0</y>
      </bounds>
      <layer>-1</layer>
      <hideInbound>false</hideInbound>
      <addResultToRunContext>false</addResultToRunContext>
      <isCriticalStep>false</isCriticalStep>
      <isNonBlocking>false</isNonBlocking>
      <isParallelStep>true</isParallelStep>
      <isSingleResponse>true</isSingleResponse>
      <recordInHistory>false</recordInHistory>
      <recordRawOutput>true</recordRawOutput>
      <recordPrimaryOutput>true</recordPrimaryOutput>
      <checkPointStep>true</checkPointStep>
      <historyCheckPointStep>true</historyCheckPointStep>
      <scriptResultStep>false</scriptResultStep>
      <userPrompt></userPrompt>
      <bindings/>
      <transitions>
        <transition id="61a85a68-a1b5-4b6b-981e-72a7959b9c09">
          <annotation></annotation>
          <name>done</name>
          <command>NEXT</command>
          <linkMode>false</linkMode>
          <responseSymbol>done</responseSymbol>
          <shouldHandoff>false</shouldHandoff>
          <transitionValue>0.0</transitionValue>
          <destination>
            <refId>c9bea484-60bf-4c0e-bdd9-f8e31d316611</refId>
          </destination>
          <source>
            <refId>c30b9644-2612-4cba-b3b5-4f151efda62b</refId>
          </source>
          <positions>
            <point>
              <x>832.0</x>
              <y>123.0</y>
            </point>
            <point>
              <x>1200.0</x>
              <y>328.0</y>
            </point>
          </positions>
          <labelPosition>
            <x>333.0</x>
            <y>0.0</y>
          </labelPosition>
        </transition>
      </transitions>
      <properties/>
      <doneResponse>
        <refId>9a87847b-d989-41ba-9d7d-35f139475d7f</refId>
      </doneResponse>
      <steps>
        <step id="20837ab0-df79-4eec-911a-78100c4d02c6">
          <annotation>05d7ad2d-d9b4-47d5-aa62-c1ffcd689a93.20837ab0-df79-4eec-911a-78100c4d02c6.description</annotation>
          <name>Blank Flow</name>
          <bounds>
            <x>910.0</x>
            <y>117.0</y>
          </bounds>
          <layer>-1</layer>
          <hideInbound>false</hideInbound>
          <addResultToRunContext>false</addResultToRunContext>
          <isCriticalStep>false</isCriticalStep>
          <isNonBlocking>false</isNonBlocking>
          <isParallelStep>false</isParallelStep>
          <isSingleResponse>false</isSingleResponse>
          <recordInHistory>false</recordInHistory>
          <recordRawOutput>true</recordRawOutput>
          <recordPrimaryOutput>true</recordPrimaryOutput>
          <checkPointStep>true</checkPointStep>
          <historyCheckPointStep>true</historyCheckPointStep>
          <scriptResultStep>false</scriptResultStep>
          <userPrompt></userPrompt>
          <bindings/>
          <transitions>
            <transition id="118c3e7f-0244-4ee5-aa03-bb8abd602ec0">
              <annotation></annotation>
              <name>success</name>
              <command>NEXT</command>
              <linkMode>false</linkMode>
              <responseSymbol>success</responseSymbol>
              <shouldHandoff>false</shouldHandoff>
              <transitionValue>0.0</transitionValue>
              <destination>
                <refId>9a87847b-d989-41ba-9d7d-35f139475d7f</refId>
              </destination>
              <source>
                <refId>20837ab0-df79-4eec-911a-78100c4d02c6</refId>
              </source>
              <positions>
                <point>
                  <x>960.0</x>
                  <y>158.0</y>
                </point>
                <point>
                  <x>1122.0</x>
                  <y>189.0</y>
                </point>
              </positions>
              <labelPosition>
                <x>333.0</x>
                <y>0.0</y>
              </labelPosition>
            </transition>
            <transition id="01d58902-cd8b-4b56-b293-ecfab176b816">
              <annotation></annotation>
              <name>failure</name>
              <command>NEXT</command>
              <linkMode>false</linkMode>
              <responseSymbol>failure</responseSymbol>
              <shouldHandoff>false</shouldHandoff>
              <transitionValue>0.0</transitionValue>
              <destination>
                <refId>9a87847b-d989-41ba-9d7d-35f139475d7f</refId>
              </destination>
              <source>
                <refId>20837ab0-df79-4eec-911a-78100c4d02c6</refId>
              </source>
              <positions>
                <point>
                  <x>960.0</x>
                  <y>158.0</y>
                </point>
                <point>
                  <x>1023.6294365938421</x>
                  <y>137.72239484130404</y>
                </point>
                <point>
                  <x>1067.7679551851436</x>
                  <y>146.16865457173827</y>
                </point>
                <point>
                  <x>1122.0</x>
                  <y>189.0</y>
                </point>
              </positions>
              <labelPosition>
                <x>333.0</x>
                <y>0.0</y>
              </labelPosition>
            </transition>
          </transitions>
          <properties/>
          <opRef>
            <refId>6671d708-26be-4ca2-887b-4adbb9550a01</refId>
          </opRef>
          <assignments/>
          <throttleSize>0</throttleSize>
        </step>
        <endBranchStep id="9a87847b-d989-41ba-9d7d-35f139475d7f">
          <annotation></annotation>
          <name>Resolved : success</name>
          <bounds>
            <x>0.0</x>
            <y>0.0</y>
          </bounds>
          <layer>-1</layer>
          <hideInbound>false</hideInbound>
          <addResultToRunContext>false</addResultToRunContext>
          <isCriticalStep>false</isCriticalStep>
          <isNonBlocking>false</isNonBlocking>
          <isParallelStep>false</isParallelStep>
          <isSingleResponse>false</isSingleResponse>
          <recordInHistory>false</recordInHistory>
          <recordRawOutput>true</recordRawOutput>
          <recordPrimaryOutput>true</recordPrimaryOutput>
          <checkPointStep>true</checkPointStep>
          <historyCheckPointStep>true</historyCheckPointStep>
          <scriptResultStep>false</scriptResultStep>
          <userPrompt></userPrompt>
          <bindings/>
          <transitions>
            <transition id="ccf9bc56-874c-40ac-96ec-8a8e006f6d96">
              <annotation></annotation>
              <name>return</name>
              <command>NEXT</command>
              <linkMode>false</linkMode>
              <responseSymbol>success</responseSymbol>
              <shouldHandoff>false</shouldHandoff>
              <transitionValue>0.0</transitionValue>
              <destination>
                <refId>9a87847b-d989-41ba-9d7d-35f139475d7f</refId>
              </destination>
              <source>
                <refId>9a87847b-d989-41ba-9d7d-35f139475d7f</refId>
              </source>
              <positions/>
            </transition>
          </transitions>
          <properties/>
        </endBranchStep>
      </steps>
      <startSteps>
        <refId>20837ab0-df79-4eec-911a-78100c4d02c6</refId>
      </startSteps>
      <lanes>
        <parallelLane id="5953a09b-227e-40d7-b40e-b19cde5ca33e">
          <annotation></annotation>
          <name></name>
          <bounds>
            <x>0.0</x>
            <y>0.0</y>
            <width>240.0</width>
            <height>140.0</height>
          </bounds>
          <parallelSteps>
            <refId>20837ab0-df79-4eec-911a-78100c4d02c6</refId>
          </parallelSteps>
          <parallelStartStep>
            <refId>20837ab0-df79-4eec-911a-78100c4d02c6</refId>
          </parallelStartStep>
        </parallelLane>
      </lanes>
      <callouts/>
      <assignments/>
      <throttleSize>0</throttleSize>
    </multiInstanceStep>
    <returnStep id="c9bea484-60bf-4c0e-bdd9-f8e31d316611">
      <annotation></annotation>
      <name>Resolved : success</name>
      <bounds>
        <x>1217.0</x>
        <y>137.0</y>
      </bounds>
      <layer>-1</layer>
      <hideInbound>false</hideInbound>
      <addResultToRunContext>false</addResultToRunContext>
      <isCriticalStep>false</isCriticalStep>
      <isNonBlocking>false</isNonBlocking>
      <isParallelStep>false</isParallelStep>
      <isSingleResponse>false</isSingleResponse>
      <recordInHistory>false</recordInHistory>
      <recordRawOutput>true</recordRawOutput>
      <recordPrimaryOutput>true</recordPrimaryOutput>
      <checkPointStep>true</checkPointStep>
      <historyCheckPointStep>true</historyCheckPointStep>
      <scriptResultStep>false</scriptResultStep>
      <userPrompt></userPrompt>
      <bindings/>
      <transitions>
        <transition id="a02a415d-29a5-4a90-8d71-9990a75037d3">
          <annotation></annotation>
          <name>return</name>
          <command>NEXT</command>
          <linkMode>false</linkMode>
          <responseSymbol>success</responseSymbol>
          <shouldHandoff>false</shouldHandoff>
          <transitionValue>0.0</transitionValue>
          <destination>
            <refId>c9bea484-60bf-4c0e-bdd9-f8e31d316611</refId>
          </destination>
          <source>
            <refId>c9bea484-60bf-4c0e-bdd9-f8e31d316611</refId>
          </source>
          <positions/>
        </transition>
      </transitions>
      <properties/>
      <returnStepType>RESOLVED</returnStepType>
      <assignments/>
    </returnStep>
  </steps>
  <startSteps>2e5cf52a-90e6-41a6-b8f2-be43410eb180</startSteps>
</flow>